[{"il":"AMASYA","ilce":"GÖYNÜCEK","mahalle":"ABACI KÖYÜ","pk":"05902"},{"il":"AMASYA","ilce":"GÖYNÜCEK","mahalle":"AFET EVLER MAH (KARAYAKUP KÖYÜ)","pk":"05902"},{"il":"AMASYA","ilce":"GÖYNÜCEK","mahalle":"AĞCAPINAR MAH (KARAYAKUP KÖYÜ)","pk":"05902"},{"il":"AMASYA","ilce":"GÖYNÜCEK","mahalle":"ALAN KÖYÜ","pk":"05902"},{"il":"AMASYA","ilce":"GÖYNÜCEK","mahalle":"ARDIÇPINAR KÖYÜ","pk":"05902"},{"il":"AMASYA","ilce":"GÖYNÜCEK","mahalle":"ARMUTDİBİ MAH (KARAYAKUP KÖYÜ)","pk":"05902"},{"il":"AMASYA","ilce":"GÖYNÜCEK","mahalle":"ASAR KÖYÜ","pk":"05902"},{"il":"AMASYA","ilce":"GÖYNÜCEK","mahalle":"AŞAĞI ÇULPARA MAH (ÇULPARA KÖYÜ)","pk":"05902"},{"il":"AMASYA","ilce":"GÖYNÜCEK","mahalle":"AŞILIK MAH (KARAYAKUP KÖYÜ)","pk":"05902"},{"il":"AMASYA","ilce":"GÖYNÜCEK","mahalle":"AYNININ ÖNÜ MAH (KARAYAKUP KÖYÜ)","pk":"05902"},{"il":"AMASYA","ilce":"GÖYNÜCEK","mahalle":"AYVALIPINAR KÖYÜ","pk":"05902"},{"il":"AMASYA","ilce":"GÖYNÜCEK","mahalle":"BAŞPINAR KÖYÜ","pk":"05902"},{"il":"AMASYA","ilce":"GÖYNÜCEK","mahalle":"BEKDEMİR KÖYÜ","pk":"05902"},{"il":"AMASYA","ilce":"GÖYNÜCEK","mahalle":"BEŞİKTEPE KÖYÜ","pk":"05902"},{"il":"AMASYA","ilce":"GÖYNÜCEK","mahalle":"CUMHURİYET MAH","pk":"05900"},{"il":"AMASYA","ilce":"GÖYNÜCEK","mahalle":"ÇAMURLU KÖYÜ","pk":"05902"},{"il":"AMASYA","ilce":"GÖYNÜCEK","mahalle":"ÇAYAN KÖYÜ","pk":"05902"},{"il":"AMASYA","ilce":"GÖYNÜCEK","mahalle":"ÇAYKIŞLA KÖYÜ","pk":"05902"},{"il":"AMASYA","ilce":"GÖYNÜCEK","mahalle":"ÇEŞMEBAŞI MAH (GEDİKSARAY KÖYÜ)","pk":"05902"},{"il":"AMASYA","ilce":"GÖYNÜCEK","mahalle":"ÇULPARA KÖYÜ","pk":"05902"},{"il":"AMASYA","ilce":"GÖYNÜCEK","mahalle":"DAVUTEVİ KÖYÜ","pk":"05902"},{"il":"AMASYA","ilce":"GÖYNÜCEK","mahalle":"GÖKÇELİ KÖYÜ","pk":"05902"},{"il":"AMASYA","ilce":"GÖYNÜCEK","mahalle":"GÜZALAN MAH (KARAYAKUP KÖYÜ)","pk":"05902"},{"il":"AMASYA","ilce":"GÖYNÜCEK","mahalle":"HARMANCIK KÖYÜ","pk":"05902"},{"il":"AMASYA","ilce":"GÖYNÜCEK","mahalle":"HASANBEY KÖYÜ","pk":"05902"},{"il":"AMASYA","ilce":"GÖYNÜCEK","mahalle":"ILISU KÖYÜ","pk":"05902"},{"il":"AMASYA","ilce":"GÖYNÜCEK","mahalle":"İKİZYAKA KÖYÜ","pk":"05902"},{"il":"AMASYA","ilce":"GÖYNÜCEK","mahalle":"KAFARLI KÖYÜ","pk":"05902"},{"il":"AMASYA","ilce":"GÖYNÜCEK","mahalle":"KARAPINAR MEVKİ MAH (İKİZYAKA KÖYÜ)","pk":"05902"},{"il":"AMASYA","ilce":"GÖYNÜCEK","mahalle":"KARAŞAR KÖYÜ","pk":"05902"},{"il":"AMASYA","ilce":"GÖYNÜCEK","mahalle":"KARAYAKUP KÖYÜ","pk":"05902"},{"il":"AMASYA","ilce":"GÖYNÜCEK","mahalle":"KERTME KÖYÜ","pk":"05902"},{"il":"AMASYA","ilce":"GÖYNÜCEK","mahalle":"KERVANSARAY KÖYÜ","pk":"05902"},{"il":"AMASYA","ilce":"GÖYNÜCEK","mahalle":"KIŞLABEYİ KÖYÜ","pk":"05902"},{"il":"AMASYA","ilce":"GÖYNÜCEK","mahalle":"KIZILÖREN MAH (TERZİKÖY KÖYÜ)","pk":"05902"},{"il":"AMASYA","ilce":"GÖYNÜCEK","mahalle":"KİLİSE MAH (KARAYAKUP KÖYÜ)","pk":"05902"},{"il":"AMASYA","ilce":"GÖYNÜCEK","mahalle":"KONURALAN KÖYÜ","pk":"05902"},{"il":"AMASYA","ilce":"GÖYNÜCEK","mahalle":"KOYUNCU KÖYÜ","pk":"05902"},{"il":"AMASYA","ilce":"GÖYNÜCEK","mahalle":"KURULUK MAH (KARAYAKUP KÖYÜ)","pk":"05902"},{"il":"AMASYA","ilce":"GÖYNÜCEK","mahalle":"KUYMA MAH (ILISU KÖYÜ)","pk":"05902"},{"il":"AMASYA","ilce":"GÖYNÜCEK","mahalle":"KUYULU KAVAKLI KÖYÜ","pk":"05902"},{"il":"AMASYA","ilce":"GÖYNÜCEK","mahalle":"KUYULU MAH (KUYULU KAVAKLI KÖYÜ)","pk":"05902"},{"il":"AMASYA","ilce":"GÖYNÜCEK","mahalle":"MERKEZ MAH","pk":"05900"},{"il":"AMASYA","ilce":"GÖYNÜCEK","mahalle":"MERKEZ MAH (DAMLAÇİMEN KÖYÜ)","pk":"05900"},{"il":"AMASYA","ilce":"GÖYNÜCEK","mahalle":"MEZRA MAH (YASSIKIŞLA KÖYÜ)","pk":"05902"},{"il":"AMASYA","ilce":"GÖYNÜCEK","mahalle":"ORTA MEVKİ MAH (İKİZYAKA KÖYÜ)","pk":"05902"},{"il":"AMASYA","ilce":"GÖYNÜCEK","mahalle":"ORTA ŞARKLI MAH (ŞARKLI KÖYÜ)","pk":"05902"},{"il":"AMASYA","ilce":"GÖYNÜCEK","mahalle":"PENPELİ KÖYÜ","pk":"05902"},{"il":"AMASYA","ilce":"GÖYNÜCEK","mahalle":"SIĞIRÇAYI KÖYÜ","pk":"05902"},{"il":"AMASYA","ilce":"GÖYNÜCEK","mahalle":"ŞARKLI KÖYÜ","pk":"05902"},{"il":"AMASYA","ilce":"GÖYNÜCEK","mahalle":"ŞIHLAR KÖYÜ","pk":"05902"},{"il":"AMASYA","ilce":"GÖYNÜCEK","mahalle":"ŞIHOĞLU KÖYÜ","pk":"05902"},{"il":"AMASYA","ilce":"GÖYNÜCEK","mahalle":"TENCİRLİ KÖYÜ","pk":"05902"},{"il":"AMASYA","ilce":"GÖYNÜCEK","mahalle":"TEPE ŞARKLI MAH (ŞARKLI KÖYÜ)","pk":"05902"},{"il":"AMASYA","ilce":"GÖYNÜCEK","mahalle":"TERZİKÖY KÖYÜ","pk":"05902"},{"il":"AMASYA","ilce":"GÖYNÜCEK","mahalle":"YASSIKIŞLA KÖYÜ","pk":"05902"},{"il":"AMASYA","ilce":"GÖYNÜCEK","mahalle":"YENİ MAH","pk":"05900"},{"il":"AMASYA","ilce":"GÖYNÜCEK","mahalle":"YENİKÖY KÖYÜ","pk":"05902"},{"il":"AMASYA","ilce":"GÖYNÜCEK","mahalle":"YEŞİLDERE MAH (GEDİKSARAY KÖYÜ)","pk":"05902"},{"il":"AMASYA","ilce":"GÖYNÜCEK","mahalle":"YEŞİLYURT MAH (TENCİRLİ KÖYÜ)","pk":"05902"}]