[{"il":"İZMİR","ilce":"ÖDEMİŞ","mahalle":"AKINCILAR MAH","pk":35750},{"il":"İZMİR","ilce":"ÖDEMİŞ","mahalle":"ALAŞARLI MAH","pk":35750},{"il":"İZMİR","ilce":"ÖDEMİŞ","mahalle":"ANAFARTALAR MAH","pk":35750},{"il":"İZMİR","ilce":"ÖDEMİŞ","mahalle":"ARTICAK MAH","pk":35750},{"il":"İZMİR","ilce":"ÖDEMİŞ","mahalle":"ATATÜRK MAH","pk":35750},{"il":"İZMİR","ilce":"ÖDEMİŞ","mahalle":"BADEMLİ MAH","pk":35750},{"il":"İZMİR","ilce":"ÖDEMİŞ","mahalle":"BALABANLI MAH","pk":35750},{"il":"İZMİR","ilce":"ÖDEMİŞ","mahalle":"BAYIRLI MAH","pk":35750},{"il":"İZMİR","ilce":"ÖDEMİŞ","mahalle":"BEBEKLER MAH","pk":35750},{"il":"İZMİR","ilce":"ÖDEMİŞ","mahalle":"BENGİSU MAH","pk":35750},{"il":"İZMİR","ilce":"ÖDEMİŞ","mahalle":"BEYAZITLAR MAH","pk":35750},{"il":"İZMİR","ilce":"ÖDEMİŞ","mahalle":"BIÇAKÇI MAH","pk":35750},{"il":"İZMİR","ilce":"ÖDEMİŞ","mahalle":"BİRGİ MAH","pk":35750},{"il":"İZMİR","ilce":"ÖDEMİŞ","mahalle":"BOZCAYAKA MAH","pk":35750},{"il":"İZMİR","ilce":"ÖDEMİŞ","mahalle":"BOZDAĞ MAH","pk":35750},{"il":"İZMİR","ilce":"ÖDEMİŞ","mahalle":"BUCAK MAH","pk":35750},{"il":"İZMİR","ilce":"ÖDEMİŞ","mahalle":"BÜLBÜLLER MAH","pk":35750},{"il":"İZMİR","ilce":"ÖDEMİŞ","mahalle":"BÜYÜKAVULCUK MAH","pk":35750},{"il":"İZMİR","ilce":"ÖDEMİŞ","mahalle":"CEVİZALAN MAH","pk":35750},{"il":"İZMİR","ilce":"ÖDEMİŞ","mahalle":"CUMHURİYET MAH","pk":35750},{"il":"İZMİR","ilce":"ÖDEMİŞ","mahalle":"ÇAĞLAYAN MAH","pk":35750},{"il":"İZMİR","ilce":"ÖDEMİŞ","mahalle":"ÇAMLICA MAH","pk":35750},{"il":"İZMİR","ilce":"ÖDEMİŞ","mahalle":"ÇAMYAYLA MAH","pk":35750},{"il":"İZMİR","ilce":"ÖDEMİŞ","mahalle":"ÇAYIR MAH","pk":35750},{"il":"İZMİR","ilce":"ÖDEMİŞ","mahalle":"ÇAYLI MAH","pk":35750},{"il":"İZMİR","ilce":"ÖDEMİŞ","mahalle":"ÇOBANLAR MAH","pk":35750},{"il":"İZMİR","ilce":"ÖDEMİŞ","mahalle":"DEMİRCİLİ MAH","pk":35750},{"il":"İZMİR","ilce":"ÖDEMİŞ","mahalle":"DEMİRDERE MAH","pk":35750},{"il":"İZMİR","ilce":"ÖDEMİŞ","mahalle":"DEREUZUNYER MAH","pk":35750},{"il":"İZMİR","ilce":"ÖDEMİŞ","mahalle":"DOLAYLAR MAH","pk":35750},{"il":"İZMİR","ilce":"ÖDEMİŞ","mahalle":"EMİRLİ MAH","pk":35750},{"il":"İZMİR","ilce":"ÖDEMİŞ","mahalle":"EMMİOĞLU MAH","pk":35750},{"il":"İZMİR","ilce":"ÖDEMİŞ","mahalle":"ERTUĞRUL MAH","pk":35750},{"il":"İZMİR","ilce":"ÖDEMİŞ","mahalle":"GERÇEKLİ MAH","pk":35750},{"il":"İZMİR","ilce":"ÖDEMİŞ","mahalle":"GERELİ MAH","pk":35750},{"il":"İZMİR","ilce":"ÖDEMİŞ","mahalle":"GÖLCÜK MAH","pk":35750},{"il":"İZMİR","ilce":"ÖDEMİŞ","mahalle":"GÜNEY MAH","pk":35750},{"il":"İZMİR","ilce":"ÖDEMİŞ","mahalle":"GÜNLÜCE MAH","pk":35750},{"il":"İZMİR","ilce":"ÖDEMİŞ","mahalle":"HACIHASAN MAH","pk":35750},{"il":"İZMİR","ilce":"ÖDEMİŞ","mahalle":"HAMAM MAH","pk":35750},{"il":"İZMİR","ilce":"ÖDEMİŞ","mahalle":"HORZUM MAH","pk":35750},{"il":"İZMİR","ilce":"ÖDEMİŞ","mahalle":"HÜRRİYET MAH","pk":35750},{"il":"İZMİR","ilce":"ÖDEMİŞ","mahalle":"IŞIK MAH","pk":35750},{"il":"İZMİR","ilce":"ÖDEMİŞ","mahalle":"İLKKURŞUN MAH","pk":35750},{"il":"İZMİR","ilce":"ÖDEMİŞ","mahalle":"İNÖNÜ MAH","pk":35750},{"il":"İZMİR","ilce":"ÖDEMİŞ","mahalle":"KARADOĞAN MAH","pk":35750},{"il":"İZMİR","ilce":"ÖDEMİŞ","mahalle":"KARAKOVA MAH","pk":35750},{"il":"İZMİR","ilce":"ÖDEMİŞ","mahalle":"KAYAKÖY MAH","pk":35750},{"il":"İZMİR","ilce":"ÖDEMİŞ","mahalle":"KAYMAKÇI MAH","pk":35750},{"il":"İZMİR","ilce":"ÖDEMİŞ","mahalle":"KAZANLI MAH","pk":35750},{"il":"İZMİR","ilce":"ÖDEMİŞ","mahalle":"KEMENLER MAH","pk":35750},{"il":"İZMİR","ilce":"ÖDEMİŞ","mahalle":"KEMER MAH","pk":35750},{"il":"İZMİR","ilce":"ÖDEMİŞ","mahalle":"KERPİÇLİK MAH","pk":35750},{"il":"İZMİR","ilce":"ÖDEMİŞ","mahalle":"KIŞLA MAH","pk":35750},{"il":"İZMİR","ilce":"ÖDEMİŞ","mahalle":"KIZILCA MAH","pk":35750},{"il":"İZMİR","ilce":"ÖDEMİŞ","mahalle":"KIZILCAAVLU MAH","pk":35750},{"il":"İZMİR","ilce":"ÖDEMİŞ","mahalle":"KONAKLI MAH","pk":35750},{"il":"İZMİR","ilce":"ÖDEMİŞ","mahalle":"KÖFÜNDERE MAH","pk":35750},{"il":"İZMİR","ilce":"ÖDEMİŞ","mahalle":"KÖSELER MAH","pk":35750},{"il":"İZMİR","ilce":"ÖDEMİŞ","mahalle":"KURUCUOVA MAH","pk":35750},{"il":"İZMİR","ilce":"ÖDEMİŞ","mahalle":"KUTLUBEYLER MAH","pk":35750},{"il":"İZMİR","ilce":"ÖDEMİŞ","mahalle":"KUVVETLİ MAH","pk":35750},{"il":"İZMİR","ilce":"ÖDEMİŞ","mahalle":"KÜÇÜKAVULCUK MAH","pk":35750},{"il":"İZMİR","ilce":"ÖDEMİŞ","mahalle":"KÜÇÜKÖREN MAH","pk":35750},{"il":"İZMİR","ilce":"ÖDEMİŞ","mahalle":"KÜRE MAH","pk":35750},{"il":"İZMİR","ilce":"ÖDEMİŞ","mahalle":"MESCİTLİ MAH","pk":35750},{"il":"İZMİR","ilce":"ÖDEMİŞ","mahalle":"MEŞRUTİYET MAH","pk":35750},{"il":"İZMİR","ilce":"ÖDEMİŞ","mahalle":"MİMAR SİNAN MAH","pk":35750},{"il":"İZMİR","ilce":"ÖDEMİŞ","mahalle":"MURSALLI MAH","pk":35750},{"il":"İZMİR","ilce":"ÖDEMİŞ","mahalle":"OCAKLI MAH","pk":35750},{"il":"İZMİR","ilce":"ÖDEMİŞ","mahalle":"OĞUZLAR MAH","pk":35750},{"il":"İZMİR","ilce":"ÖDEMİŞ","mahalle":"ORHANGAZİ MAH","pk":35750},{"il":"İZMİR","ilce":"ÖDEMİŞ","mahalle":"ORTAKÖY MAH","pk":35750},{"il":"İZMİR","ilce":"ÖDEMİŞ","mahalle":"OVACIK MAH","pk":35750},{"il":"İZMİR","ilce":"ÖDEMİŞ","mahalle":"OVAKENT MAH","pk":35750},{"il":"İZMİR","ilce":"ÖDEMİŞ","mahalle":"PİRİNÇÇİ MAH","pk":35750},{"il":"İZMİR","ilce":"ÖDEMİŞ","mahalle":"SEKİKÖY MAH","pk":35750},{"il":"İZMİR","ilce":"ÖDEMİŞ","mahalle":"SEYREKLİ MAH","pk":35750},{"il":"İZMİR","ilce":"ÖDEMİŞ","mahalle":"SUÇIKTI MAH","pk":35750},{"il":"İZMİR","ilce":"ÖDEMİŞ","mahalle":"SÜLEYMAN DEMİREL MAH","pk":35750},{"il":"İZMİR","ilce":"ÖDEMİŞ","mahalle":"SÜLEYMANLAR MAH","pk":35750},{"il":"İZMİR","ilce":"ÖDEMİŞ","mahalle":"ŞİRİNKÖY MAH","pk":35750},{"il":"İZMİR","ilce":"ÖDEMİŞ","mahalle":"TEKKE MAH","pk":35750},{"il":"İZMİR","ilce":"ÖDEMİŞ","mahalle":"TOSUNLAR MAH","pk":35750},{"il":"İZMİR","ilce":"ÖDEMİŞ","mahalle":"TÜRKMEN MAH","pk":35750},{"il":"İZMİR","ilce":"ÖDEMİŞ","mahalle":"TÜRKÖNÜ MAH","pk":35750},{"il":"İZMİR","ilce":"ÖDEMİŞ","mahalle":"UMURBEY MAH","pk":35750},{"il":"İZMİR","ilce":"ÖDEMİŞ","mahalle":"UZUNDERE MAH","pk":35750},{"il":"İZMİR","ilce":"ÖDEMİŞ","mahalle":"ÜÇ EYLÜL MAH","pk":35750},{"il":"İZMİR","ilce":"ÖDEMİŞ","mahalle":"ÜÇKONAK MAH","pk":35750},{"il":"İZMİR","ilce":"ÖDEMİŞ","mahalle":"ÜZÜMLÜ MAH","pk":35750},{"il":"İZMİR","ilce":"ÖDEMİŞ","mahalle":"VELİLER MAH","pk":35750},{"il":"İZMİR","ilce":"ÖDEMİŞ","mahalle":"YENİCEKÖY MAH","pk":35750},{"il":"İZMİR","ilce":"ÖDEMİŞ","mahalle":"YENİKÖY MAH","pk":35750},{"il":"İZMİR","ilce":"ÖDEMİŞ","mahalle":"YEŞİLKÖY MAH","pk":35750},{"il":"İZMİR","ilce":"ÖDEMİŞ","mahalle":"YILANLI MAH","pk":35750},{"il":"İZMİR","ilce":"ÖDEMİŞ","mahalle":"YOLÜSTÜ MAH","pk":35750},{"il":"İZMİR","ilce":"ÖDEMİŞ","mahalle":"YUSUFDERE MAH","pk":35750},{"il":"İZMİR","ilce":"ÖDEMİŞ","mahalle":"ZAFER MAH","pk":35750}]