[{"il":"KARS","ilce":"SELİM","mahalle":"AKÇAKALE KÖYÜ","pk":36902},{"il":"KARS","ilce":"SELİM","mahalle":"AKPINAR KÖYÜ","pk":36902},{"il":"KARS","ilce":"SELİM","mahalle":"ALİSOFU KÖYÜ","pk":36902},{"il":"KARS","ilce":"SELİM","mahalle":"AŞAĞI MAH (BÖLÜKBAŞ KÖYÜ)","pk":36902},{"il":"KARS","ilce":"SELİM","mahalle":"AŞAĞI MAH (BÜYÜKDERE KÖYÜ)","pk":36902},{"il":"KARS","ilce":"SELİM","mahalle":"AŞAĞI MAH (İĞDİR KÖYÜ)","pk":36902},{"il":"KARS","ilce":"SELİM","mahalle":"AŞAĞI MAH (KATRANLI KÖYÜ)","pk":36902},{"il":"KARS","ilce":"SELİM","mahalle":"AŞAĞI MAH (KOYUNYURDU KÖYÜ)","pk":36902},{"il":"KARS","ilce":"SELİM","mahalle":"AŞAĞIDAMLAPINAR KÖYÜ","pk":36902},{"il":"KARS","ilce":"SELİM","mahalle":"AŞAĞIKOTANLI KÖYÜ","pk":36902},{"il":"KARS","ilce":"SELİM","mahalle":"BAŞKÖY KÖYÜ","pk":36902},{"il":"KARS","ilce":"SELİM","mahalle":"BAYKARA KÖYÜ","pk":36902},{"il":"KARS","ilce":"SELİM","mahalle":"BENLİAHMET KÖYÜ","pk":36902},{"il":"KARS","ilce":"SELİM","mahalle":"BEYKÖY KÖYÜ","pk":36902},{"il":"KARS","ilce":"SELİM","mahalle":"BOZKUŞ KÖYÜ","pk":36902},{"il":"KARS","ilce":"SELİM","mahalle":"BÜYÜK OLUKLU KÖYÜ","pk":36902},{"il":"KARS","ilce":"SELİM","mahalle":"CAMİ ALTI MAH (HASBEY KÖYÜ)","pk":36902},{"il":"KARS","ilce":"SELİM","mahalle":"CAMİ ÜSTÜ MAH (HASBEY KÖYÜ)","pk":36902},{"il":"KARS","ilce":"SELİM","mahalle":"CAMİİ MAH (BAYBURT KÖYÜ)","pk":36902},{"il":"KARS","ilce":"SELİM","mahalle":"CAVLAK KÖYÜ","pk":36902},{"il":"KARS","ilce":"SELİM","mahalle":"CUMHURİYET MAH","pk":36900},{"il":"KARS","ilce":"SELİM","mahalle":"ÇARŞI MAH","pk":36900},{"il":"KARS","ilce":"SELİM","mahalle":"ÇAYBAŞI KÖYÜ","pk":36902},{"il":"KARS","ilce":"SELİM","mahalle":"ÇIPLAKLI KÖYÜ","pk":36902},{"il":"KARS","ilce":"SELİM","mahalle":"DARBOĞAZ KÖYÜ","pk":36902},{"il":"KARS","ilce":"SELİM","mahalle":"DEĞİRMEN MAH (İĞDİR KÖYÜ)","pk":36902},{"il":"KARS","ilce":"SELİM","mahalle":"DEĞİRMENBAŞI MAH (AKYAR KÖYÜ)","pk":36902},{"il":"KARS","ilce":"SELİM","mahalle":"DÖLBENTLİ KÖYÜ","pk":36902},{"il":"KARS","ilce":"SELİM","mahalle":"ESKİGAZİ KÖYÜ","pk":36902},{"il":"KARS","ilce":"SELİM","mahalle":"ESKİGEÇİT KÖYÜ","pk":36902},{"il":"KARS","ilce":"SELİM","mahalle":"GELİNALAN KÖYÜ","pk":36902},{"il":"KARS","ilce":"SELİM","mahalle":"GİRİŞ MAH (HASBEY KÖYÜ)","pk":36902},{"il":"KARS","ilce":"SELİM","mahalle":"GÜRBÜZLER KÖYÜ","pk":36902},{"il":"KARS","ilce":"SELİM","mahalle":"KAMIŞLI KÖYÜ","pk":36902},{"il":"KARS","ilce":"SELİM","mahalle":"KARAÇAYIR KÖYÜ","pk":36902},{"il":"KARS","ilce":"SELİM","mahalle":"KARAHAMZA KÖYÜ","pk":36902},{"il":"KARS","ilce":"SELİM","mahalle":"KARAKALE KÖYÜ","pk":36902},{"il":"KARS","ilce":"SELİM","mahalle":"KAYNARLI KÖYÜ","pk":36902},{"il":"KARS","ilce":"SELİM","mahalle":"KEKEÇ KÖYÜ","pk":36902},{"il":"KARS","ilce":"SELİM","mahalle":"KIRKPINAR KÖYÜ","pk":36902},{"il":"KARS","ilce":"SELİM","mahalle":"KOŞAPINAR KÖYÜ","pk":36902},{"il":"KARS","ilce":"SELİM","mahalle":"KÖPRÜBAŞI MAH","pk":36900},{"il":"KARS","ilce":"SELİM","mahalle":"LALOĞLU KÖYÜ","pk":36902},{"il":"KARS","ilce":"SELİM","mahalle":"MOLLAMUSTAFA KÖYÜ","pk":36902},{"il":"KARS","ilce":"SELİM","mahalle":"OKUL MAH (BAYBURT KÖYÜ)","pk":36902},{"il":"KARS","ilce":"SELİM","mahalle":"OKUL MAH (HASBEY KÖYÜ)","pk":36902},{"il":"KARS","ilce":"SELİM","mahalle":"OLUKLU KÖYÜ","pk":36902},{"il":"KARS","ilce":"SELİM","mahalle":"ORTA MAH (AKYAR KÖYÜ)","pk":36902},{"il":"KARS","ilce":"SELİM","mahalle":"ORTAKALE KÖYÜ","pk":36902},{"il":"KARS","ilce":"SELİM","mahalle":"SARIGÜN KÖYÜ","pk":36902},{"il":"KARS","ilce":"SELİM","mahalle":"SÖĞÜTLÜ KÖYÜ","pk":36902},{"il":"KARS","ilce":"SELİM","mahalle":"TEPE MAH (AKYAR KÖYÜ)","pk":36902},{"il":"KARS","ilce":"SELİM","mahalle":"TOZLUCA KÖYÜ","pk":36902},{"il":"KARS","ilce":"SELİM","mahalle":"TUYGUN KÖYÜ","pk":36902},{"il":"KARS","ilce":"SELİM","mahalle":"YALNIZÇAM KÖYÜ","pk":36902},{"il":"KARS","ilce":"SELİM","mahalle":"YAMAÇLI KÖYÜ","pk":36902},{"il":"KARS","ilce":"SELİM","mahalle":"YASSICA KÖYÜ","pk":36902},{"il":"KARS","ilce":"SELİM","mahalle":"YAYLACIK KÖYÜ","pk":36902},{"il":"KARS","ilce":"SELİM","mahalle":"YENİCE KÖYÜ","pk":36902},{"il":"KARS","ilce":"SELİM","mahalle":"YEŞİLTEPE KÖYÜ","pk":36902},{"il":"KARS","ilce":"SELİM","mahalle":"YOLGEÇMEZ KÖYÜ","pk":36902},{"il":"KARS","ilce":"SELİM","mahalle":"YUKARI MAH (BÖLÜKBAŞ KÖYÜ)","pk":36902},{"il":"KARS","ilce":"SELİM","mahalle":"YUKARI MAH (BÜYÜKDERE KÖYÜ)","pk":36902},{"il":"KARS","ilce":"SELİM","mahalle":"YUKARI MAH (İĞDİR KÖYÜ)","pk":36902},{"il":"KARS","ilce":"SELİM","mahalle":"YUKARI MAH (KATRANLI KÖYÜ)","pk":36902},{"il":"KARS","ilce":"SELİM","mahalle":"YUKARI MAH (KOYUNYURDU KÖYÜ)","pk":36902},{"il":"KARS","ilce":"SELİM","mahalle":"YUKARIDAMLAPINAR KÖYÜ","pk":36902},{"il":"KARS","ilce":"SELİM","mahalle":"YUKARIKOTANLI KÖYÜ","pk":36902}]