[{"il":"KAYSERİ","ilce":"DEVELİ","mahalle":"ABDULBAKİ MAH","pk":38400},{"il":"KAYSERİ","ilce":"DEVELİ","mahalle":"ALPASLAN MAH","pk":38400},{"il":"KAYSERİ","ilce":"DEVELİ","mahalle":"AŞAĞIEVEREK MAH","pk":38400},{"il":"KAYSERİ","ilce":"DEVELİ","mahalle":"AŞIK SEYRANİ MAH","pk":38400},{"il":"KAYSERİ","ilce":"DEVELİ","mahalle":"AYŞEPINAR MAH","pk":38400},{"il":"KAYSERİ","ilce":"DEVELİ","mahalle":"AYVAZHACI MAH","pk":38400},{"il":"KAYSERİ","ilce":"DEVELİ","mahalle":"BAHÇEBAŞI MAH","pk":38400},{"il":"KAYSERİ","ilce":"DEVELİ","mahalle":"BAHÇELİEVLER MAH","pk":38400},{"il":"KAYSERİ","ilce":"DEVELİ","mahalle":"BÜYÜKKÜNYE MAH","pk":38400},{"il":"KAYSERİ","ilce":"DEVELİ","mahalle":"CAMİİCEDİT MAH","pk":38400},{"il":"KAYSERİ","ilce":"DEVELİ","mahalle":"CUMHURİYET MAH","pk":38400},{"il":"KAYSERİ","ilce":"DEVELİ","mahalle":"ÇADIRYERİ MAH","pk":38400},{"il":"KAYSERİ","ilce":"DEVELİ","mahalle":"ÇATALOLUK MAH","pk":38400},{"il":"KAYSERİ","ilce":"DEVELİ","mahalle":"ÇAYIRÖZÜ MAH","pk":38400},{"il":"KAYSERİ","ilce":"DEVELİ","mahalle":"ÇAYLICA MAH","pk":38400},{"il":"KAYSERİ","ilce":"DEVELİ","mahalle":"ÇOMAKLI MAH","pk":38400},{"il":"KAYSERİ","ilce":"DEVELİ","mahalle":"ÇÖTEN MAH","pk":38400},{"il":"KAYSERİ","ilce":"DEVELİ","mahalle":"ÇUKURYURT MAH","pk":38400},{"il":"KAYSERİ","ilce":"DEVELİ","mahalle":"DEREBAŞI MAH","pk":38400},{"il":"KAYSERİ","ilce":"DEVELİ","mahalle":"DEREŞİMLİ MAH","pk":38400},{"il":"KAYSERİ","ilce":"DEVELİ","mahalle":"DEVELİ CAMİKEBİR MAH","pk":38400},{"il":"KAYSERİ","ilce":"DEVELİ","mahalle":"E.CAMİİKEBİR MAH","pk":38400},{"il":"KAYSERİ","ilce":"DEVELİ","mahalle":"EPÇE MAH","pk":38400},{"il":"KAYSERİ","ilce":"DEVELİ","mahalle":"EŞELİK MAH","pk":38400},{"il":"KAYSERİ","ilce":"DEVELİ","mahalle":"FATİH MAH","pk":38400},{"il":"KAYSERİ","ilce":"DEVELİ","mahalle":"FENESEAŞAĞI MAH","pk":38400},{"il":"KAYSERİ","ilce":"DEVELİ","mahalle":"FENESEYUKARI MAH","pk":38400},{"il":"KAYSERİ","ilce":"DEVELİ","mahalle":"GAZİ MAH","pk":38400},{"il":"KAYSERİ","ilce":"DEVELİ","mahalle":"GÖMEDİ MAH","pk":38400},{"il":"KAYSERİ","ilce":"DEVELİ","mahalle":"GÜMÜŞÖREN MAH","pk":38400},{"il":"KAYSERİ","ilce":"DEVELİ","mahalle":"GÜNEYAŞAĞI MAH","pk":38400},{"il":"KAYSERİ","ilce":"DEVELİ","mahalle":"GÜNEYYUKARI MAH","pk":38400},{"il":"KAYSERİ","ilce":"DEVELİ","mahalle":"HARMAN MAH","pk":38400},{"il":"KAYSERİ","ilce":"DEVELİ","mahalle":"HAVADAN MAH","pk":38400},{"il":"KAYSERİ","ilce":"DEVELİ","mahalle":"HOŞÇA MAH","pk":38400},{"il":"KAYSERİ","ilce":"DEVELİ","mahalle":"HÜSEYİNLİ MAH","pk":38400},{"il":"KAYSERİ","ilce":"DEVELİ","mahalle":"İBRAHİMAĞA MAH","pk":38400},{"il":"KAYSERİ","ilce":"DEVELİ","mahalle":"İNCESU MAH","pk":38400},{"il":"KAYSERİ","ilce":"DEVELİ","mahalle":"İZMİRLİ MAH","pk":38400},{"il":"KAYSERİ","ilce":"DEVELİ","mahalle":"KABAKLI MAH","pk":38400},{"il":"KAYSERİ","ilce":"DEVELİ","mahalle":"KALEKÖY MAH","pk":38400},{"il":"KAYSERİ","ilce":"DEVELİ","mahalle":"KARACAÖREN MAH","pk":38400},{"il":"KAYSERİ","ilce":"DEVELİ","mahalle":"KILIÇKAYA MAH","pk":38400},{"il":"KAYSERİ","ilce":"DEVELİ","mahalle":"KIZIK MAH","pk":38400},{"il":"KAYSERİ","ilce":"DEVELİ","mahalle":"KOPÇULLU MAH","pk":38400},{"il":"KAYSERİ","ilce":"DEVELİ","mahalle":"KOZLUCA MAH","pk":38400},{"il":"KAYSERİ","ilce":"DEVELİ","mahalle":"KÖSELER MAH","pk":38400},{"il":"KAYSERİ","ilce":"DEVELİ","mahalle":"KULPAK MAH","pk":38400},{"il":"KAYSERİ","ilce":"DEVELİ","mahalle":"KÜÇÜKKÜNYE MAH","pk":38400},{"il":"KAYSERİ","ilce":"DEVELİ","mahalle":"MEHMET AKİF ERSOY MAH","pk":38400},{"il":"KAYSERİ","ilce":"DEVELİ","mahalle":"MİLLİDERE MAH","pk":38400},{"il":"KAYSERİ","ilce":"DEVELİ","mahalle":"MUSTAFA ASIM KÖKSAL MAH","pk":38400},{"il":"KAYSERİ","ilce":"DEVELİ","mahalle":"ÖKSÜT MAH","pk":38400},{"il":"KAYSERİ","ilce":"DEVELİ","mahalle":"REŞADİYE MAH","pk":38400},{"il":"KAYSERİ","ilce":"DEVELİ","mahalle":"SARAYCIK MAH","pk":38400},{"il":"KAYSERİ","ilce":"DEVELİ","mahalle":"SARICA MAH","pk":38400},{"il":"KAYSERİ","ilce":"DEVELİ","mahalle":"SARIKAYA MAH","pk":38400},{"il":"KAYSERİ","ilce":"DEVELİ","mahalle":"SATI MAH","pk":38400},{"il":"KAYSERİ","ilce":"DEVELİ","mahalle":"SİNDELHÖYÜK CAMİKEBİR MAH","pk":38400},{"il":"KAYSERİ","ilce":"DEVELİ","mahalle":"SİNDELHÖYÜK FATİH MAH","pk":38400},{"il":"KAYSERİ","ilce":"DEVELİ","mahalle":"SİNDELHÖYÜK YENİCE MAH","pk":38400},{"il":"KAYSERİ","ilce":"DEVELİ","mahalle":"SOYSALLI MAH","pk":38400},{"il":"KAYSERİ","ilce":"DEVELİ","mahalle":"ŞAHMELİK MAH","pk":38400},{"il":"KAYSERİ","ilce":"DEVELİ","mahalle":"ŞHT.ÜSTĞM.HASAN ŞAHAN MAH","pk":38400},{"il":"KAYSERİ","ilce":"DEVELİ","mahalle":"ŞIHLI MAH","pk":38400},{"il":"KAYSERİ","ilce":"DEVELİ","mahalle":"TAŞCI BUCAK MERKEZİ MAH","pk":38400},{"il":"KAYSERİ","ilce":"DEVELİ","mahalle":"TOMBAK MAH","pk":38400},{"il":"KAYSERİ","ilce":"DEVELİ","mahalle":"YAYLACIK MAH","pk":38400},{"il":"KAYSERİ","ilce":"DEVELİ","mahalle":"YAZIBAŞI MAH","pk":38400},{"il":"KAYSERİ","ilce":"DEVELİ","mahalle":"YEDEK MAH","pk":38400},{"il":"KAYSERİ","ilce":"DEVELİ","mahalle":"YENİ MAH","pk":38400},{"il":"KAYSERİ","ilce":"DEVELİ","mahalle":"YENİCE MAH","pk":38400},{"il":"KAYSERİ","ilce":"DEVELİ","mahalle":"YENİHAYAT MAH","pk":38400},{"il":"KAYSERİ","ilce":"DEVELİ","mahalle":"YENİKÖY MAH","pk":38400},{"il":"KAYSERİ","ilce":"DEVELİ","mahalle":"YEŞİLYURT MAH","pk":38400},{"il":"KAYSERİ","ilce":"DEVELİ","mahalle":"YÜZEVLER MAH","pk":38400},{"il":"KAYSERİ","ilce":"DEVELİ","mahalle":"ZİLE MAH","pk":38400}]