[{"il":"MERSİN","ilce":"MUT","mahalle":"ALAÇAM MAH","pk":33600},{"il":"MERSİN","ilce":"MUT","mahalle":"AŞAĞIKÖSELERLİ MAH","pk":33600},{"il":"MERSİN","ilce":"MUT","mahalle":"AYDINOĞLU MAH","pk":33600},{"il":"MERSİN","ilce":"MUT","mahalle":"BAĞCAĞIZ MAH","pk":33600},{"il":"MERSİN","ilce":"MUT","mahalle":"BALLI MAH","pk":33600},{"il":"MERSİN","ilce":"MUT","mahalle":"BARABANLI MAH","pk":33600},{"il":"MERSİN","ilce":"MUT","mahalle":"BOZDOĞAN MAH","pk":33600},{"il":"MERSİN","ilce":"MUT","mahalle":"BURUNKÖY MAH","pk":33600},{"il":"MERSİN","ilce":"MUT","mahalle":"CERİTLER MAH","pk":33600},{"il":"MERSİN","ilce":"MUT","mahalle":"CUMHURİYET MAH","pk":33600},{"il":"MERSİN","ilce":"MUT","mahalle":"ÇAĞLAYANGEDİK MAH","pk":33600},{"il":"MERSİN","ilce":"MUT","mahalle":"ÇALTILI MAH","pk":33600},{"il":"MERSİN","ilce":"MUT","mahalle":"ÇAMLICA MAH","pk":33600},{"il":"MERSİN","ilce":"MUT","mahalle":"ÇAMPINAR MAH","pk":33600},{"il":"MERSİN","ilce":"MUT","mahalle":"ÇATAKBAĞ MAH","pk":33600},{"il":"MERSİN","ilce":"MUT","mahalle":"ÇATALHARMAN MAH","pk":33600},{"il":"MERSİN","ilce":"MUT","mahalle":"ÇINARLI MAH","pk":33600},{"il":"MERSİN","ilce":"MUT","mahalle":"ÇİVİ MAH","pk":33600},{"il":"MERSİN","ilce":"MUT","mahalle":"ÇORTAK MAH","pk":33600},{"il":"MERSİN","ilce":"MUT","mahalle":"ÇÖMELEK MAH","pk":33600},{"il":"MERSİN","ilce":"MUT","mahalle":"ÇUKURBAĞ MAH","pk":33600},{"il":"MERSİN","ilce":"MUT","mahalle":"DAĞPAZARI MAH","pk":33600},{"il":"MERSİN","ilce":"MUT","mahalle":"DEMİRKAPI MAH","pk":33600},{"il":"MERSİN","ilce":"MUT","mahalle":"DEREKÖY MAH","pk":33600},{"il":"MERSİN","ilce":"MUT","mahalle":"DERİNÇAY MAH","pk":33600},{"il":"MERSİN","ilce":"MUT","mahalle":"DEVECİ MAH","pk":33600},{"il":"MERSİN","ilce":"MUT","mahalle":"DİŞTAŞ MAH","pk":33600},{"il":"MERSİN","ilce":"MUT","mahalle":"DOĞANCI MAH","pk":33600},{"il":"MERSİN","ilce":"MUT","mahalle":"ELBEYLİ MAH","pk":33600},{"il":"MERSİN","ilce":"MUT","mahalle":"ELMAPINAR MAH","pk":33600},{"il":"MERSİN","ilce":"MUT","mahalle":"ESENÇAY MAH","pk":33600},{"il":"MERSİN","ilce":"MUT","mahalle":"EVREN MAH","pk":33600},{"il":"MERSİN","ilce":"MUT","mahalle":"FAKIRCA MAH","pk":33600},{"il":"MERSİN","ilce":"MUT","mahalle":"GEÇİMLİ MAH","pk":33600},{"il":"MERSİN","ilce":"MUT","mahalle":"GENÇALİ MAH","pk":33600},{"il":"MERSİN","ilce":"MUT","mahalle":"GÖCEKLER MAH","pk":33600},{"il":"MERSİN","ilce":"MUT","mahalle":"GÖKÇETAŞ MAH","pk":33600},{"il":"MERSİN","ilce":"MUT","mahalle":"GÖKSU MAH","pk":33600},{"il":"MERSİN","ilce":"MUT","mahalle":"GÜLLÜK MAH","pk":33600},{"il":"MERSİN","ilce":"MUT","mahalle":"GÜME MAH","pk":33600},{"il":"MERSİN","ilce":"MUT","mahalle":"GÜZELKÖY MAH","pk":33600},{"il":"MERSİN","ilce":"MUT","mahalle":"GÜZELYURT MAH","pk":33600},{"il":"MERSİN","ilce":"MUT","mahalle":"HACIAHMETLİ MAH","pk":33600},{"il":"MERSİN","ilce":"MUT","mahalle":"HACIİLYASLI MAH","pk":33600},{"il":"MERSİN","ilce":"MUT","mahalle":"HACINUHLU MAH","pk":33600},{"il":"MERSİN","ilce":"MUT","mahalle":"HACISAİT MAH","pk":33600},{"il":"MERSİN","ilce":"MUT","mahalle":"HAMAM MAH","pk":33600},{"il":"MERSİN","ilce":"MUT","mahalle":"HAYDARKÖY MAH","pk":33600},{"il":"MERSİN","ilce":"MUT","mahalle":"HİSARKÖY MAH","pk":33600},{"il":"MERSİN","ilce":"MUT","mahalle":"HOCALI MAH","pk":33600},{"il":"MERSİN","ilce":"MUT","mahalle":"ILICA MAH","pk":33600},{"il":"MERSİN","ilce":"MUT","mahalle":"IRMAKLI MAH","pk":33600},{"il":"MERSİN","ilce":"MUT","mahalle":"IŞIKLAR MAH","pk":33600},{"il":"MERSİN","ilce":"MUT","mahalle":"İBRAHİMLİ MAH","pk":33600},{"il":"MERSİN","ilce":"MUT","mahalle":"KADIKÖY MAH","pk":33600},{"il":"MERSİN","ilce":"MUT","mahalle":"KALE MAH","pk":33600},{"il":"MERSİN","ilce":"MUT","mahalle":"KARACAOĞLAN MAH","pk":33600},{"il":"MERSİN","ilce":"MUT","mahalle":"KARADİKEN MAH","pk":33600},{"il":"MERSİN","ilce":"MUT","mahalle":"KARŞIYAKA MAH","pk":33600},{"il":"MERSİN","ilce":"MUT","mahalle":"KAVAKLI MAH","pk":33600},{"il":"MERSİN","ilce":"MUT","mahalle":"KAVAKÖZÜ MAH","pk":33600},{"il":"MERSİN","ilce":"MUT","mahalle":"KAYABAŞI MAH","pk":33600},{"il":"MERSİN","ilce":"MUT","mahalle":"KAYAÖNÜ MAH","pk":33600},{"il":"MERSİN","ilce":"MUT","mahalle":"KELCEKÖY MAH","pk":33600},{"il":"MERSİN","ilce":"MUT","mahalle":"KEMENLİ MAH","pk":33600},{"il":"MERSİN","ilce":"MUT","mahalle":"KIRKKAVAK MAH","pk":33600},{"il":"MERSİN","ilce":"MUT","mahalle":"KIŞLAKÖY MAH","pk":33600},{"il":"MERSİN","ilce":"MUT","mahalle":"KIZILALAN MAH","pk":33600},{"il":"MERSİN","ilce":"MUT","mahalle":"KÖSELERLİ MAH","pk":33600},{"il":"MERSİN","ilce":"MUT","mahalle":"KUMAÇUKURU MAH","pk":33600},{"il":"MERSİN","ilce":"MUT","mahalle":"KURTSUYU MAH","pk":33600},{"il":"MERSİN","ilce":"MUT","mahalle":"KURTULUŞ MAH","pk":33600},{"il":"MERSİN","ilce":"MUT","mahalle":"KÜLTÜR MAH","pk":33600},{"il":"MERSİN","ilce":"MUT","mahalle":"KÜRKÇÜ MAH","pk":33600},{"il":"MERSİN","ilce":"MUT","mahalle":"MEYDAN MAH","pk":33600},{"il":"MERSİN","ilce":"MUT","mahalle":"MİRAHOR MAH","pk":33600},{"il":"MERSİN","ilce":"MUT","mahalle":"MUCUK MAH","pk":33600},{"il":"MERSİN","ilce":"MUT","mahalle":"NARLI MAH","pk":33600},{"il":"MERSİN","ilce":"MUT","mahalle":"NARLIDERE MAH","pk":33600},{"il":"MERSİN","ilce":"MUT","mahalle":"ORTAKÖY MAH","pk":33600},{"il":"MERSİN","ilce":"MUT","mahalle":"ÖZKÖY MAH","pk":33600},{"il":"MERSİN","ilce":"MUT","mahalle":"ÖZLÜ MAH","pk":33600},{"il":"MERSİN","ilce":"MUT","mahalle":"PALANTEPE MAH","pk":33600},{"il":"MERSİN","ilce":"MUT","mahalle":"PAMUKLU MAH","pk":33600},{"il":"MERSİN","ilce":"MUT","mahalle":"PINARBAŞI MAH","pk":33600},{"il":"MERSİN","ilce":"MUT","mahalle":"SAKIZ MAH","pk":33600},{"il":"MERSİN","ilce":"MUT","mahalle":"SARIVELİLER MAH","pk":33600},{"il":"MERSİN","ilce":"MUT","mahalle":"SELAMLI MAH","pk":33600},{"il":"MERSİN","ilce":"MUT","mahalle":"SUÇATI MAH","pk":33600},{"il":"MERSİN","ilce":"MUT","mahalle":"TEKELİ MAH","pk":33600},{"il":"MERSİN","ilce":"MUT","mahalle":"TOpkAYA MAH","pk":33600},{"il":"MERSİN","ilce":"MUT","mahalle":"TOPLUCA MAH","pk":33600},{"il":"MERSİN","ilce":"MUT","mahalle":"TUĞRUL MAH","pk":33600},{"il":"MERSİN","ilce":"MUT","mahalle":"YALNIZCABAĞ MAH","pk":33600},{"il":"MERSİN","ilce":"MUT","mahalle":"YAPINTI MAH","pk":33600},{"il":"MERSİN","ilce":"MUT","mahalle":"YATIRTAŞ MAH","pk":33600},{"il":"MERSİN","ilce":"MUT","mahalle":"YAZALANI MAH","pk":33600},{"il":"MERSİN","ilce":"MUT","mahalle":"YEŞİLKÖY MAH","pk":33600},{"il":"MERSİN","ilce":"MUT","mahalle":"YEŞİLYURT MAH","pk":33600},{"il":"MERSİN","ilce":"MUT","mahalle":"YILDIZKÖY MAH","pk":33600},{"il":"MERSİN","ilce":"MUT","mahalle":"YUKARIKÖSELERLİ MAH","pk":33600},{"il":"MERSİN","ilce":"MUT","mahalle":"ZEYTİNÇUKURU MAH","pk":33600}]