[{"il":"MUĞLA","ilce":"KÖYCEĞİZ","mahalle":"AKKÖPRÜ MAH","pk":48800},{"il":"MUĞLA","ilce":"KÖYCEĞİZ","mahalle":"BALCILAR MAH","pk":48800},{"il":"MUĞLA","ilce":"KÖYCEĞİZ","mahalle":"BEYOBASI MAH","pk":48800},{"il":"MUĞLA","ilce":"KÖYCEĞİZ","mahalle":"ÇANDIR MAH","pk":48800},{"il":"MUĞLA","ilce":"KÖYCEĞİZ","mahalle":"ÇAYHİSAR MAH","pk":48800},{"il":"MUĞLA","ilce":"KÖYCEĞİZ","mahalle":"DÖĞÜŞBELEN MAH","pk":48800},{"il":"MUĞLA","ilce":"KÖYCEĞİZ","mahalle":"EKİNCİK MAH","pk":48800},{"il":"MUĞLA","ilce":"KÖYCEĞİZ","mahalle":"GELİŞİM MAH","pk":48800},{"il":"MUĞLA","ilce":"KÖYCEĞİZ","mahalle":"GÜLPINAR MAH","pk":48800},{"il":"MUĞLA","ilce":"KÖYCEĞİZ","mahalle":"HAMİTKÖY MAH","pk":48800},{"il":"MUĞLA","ilce":"KÖYCEĞİZ","mahalle":"KARAÇAM MAH","pk":48800},{"il":"MUĞLA","ilce":"KÖYCEĞİZ","mahalle":"KAVAKARASI MAH","pk":48800},{"il":"MUĞLA","ilce":"KÖYCEĞİZ","mahalle":"KÖYCEĞİZ MAH","pk":48800},{"il":"MUĞLA","ilce":"KÖYCEĞİZ","mahalle":"OTMANLAR MAH","pk":48800},{"il":"MUĞLA","ilce":"KÖYCEĞİZ","mahalle":"PINAR MAH","pk":48800},{"il":"MUĞLA","ilce":"KÖYCEĞİZ","mahalle":"SAZAK MAH","pk":48800},{"il":"MUĞLA","ilce":"KÖYCEĞİZ","mahalle":"SULTANİYE MAH","pk":48800},{"il":"MUĞLA","ilce":"KÖYCEĞİZ","mahalle":"TOPARLAR MAH","pk":48800},{"il":"MUĞLA","ilce":"KÖYCEĞİZ","mahalle":"ULUCAMİ MAH","pk":48800},{"il":"MUĞLA","ilce":"KÖYCEĞİZ","mahalle":"YANGI MAH","pk":48800},{"il":"MUĞLA","ilce":"KÖYCEĞİZ","mahalle":"YAYLA MAH","pk":48800},{"il":"MUĞLA","ilce":"KÖYCEĞİZ","mahalle":"YENİ MAH","pk":48800},{"il":"MUĞLA","ilce":"KÖYCEĞİZ","mahalle":"YEŞİLKÖY MAH","pk":48800},{"il":"MUĞLA","ilce":"KÖYCEĞİZ","mahalle":"ZAFERLER MAH","pk":48800},{"il":"MUĞLA","ilce":"KÖYCEĞİZ","mahalle":"ZEYTİNALANI MAH","pk":48800}]