[{"il":"RİZE","ilce":"ARDEŞEN","mahalle":"AÇIKMEŞE MAH (ÇIRAKLAR KÖYÜ)","pk":53480},{"il":"RİZE","ilce":"ARDEŞEN","mahalle":"ADA MAH (TUNCA BELDESİ)","pk":53490},{"il":"RİZE","ilce":"ARDEŞEN","mahalle":"AKARSU MAH (GÜNEY KÖYÜ)","pk":53480},{"il":"RİZE","ilce":"ARDEŞEN","mahalle":"AKPINAR MAH (AKDERE KÖYÜ)","pk":53480},{"il":"RİZE","ilce":"ARDEŞEN","mahalle":"ALİ EFENDİ MAH (ORTAALAN KÖYÜ)","pk":53480},{"il":"RİZE","ilce":"ARDEŞEN","mahalle":"ALT MAH (MANGANEZ KÖYÜ)","pk":53480},{"il":"RİZE","ilce":"ARDEŞEN","mahalle":"ALT MAH (PINARLI KÖYÜ)","pk":53480},{"il":"RİZE","ilce":"ARDEŞEN","mahalle":"ARICILAR KÖYÜ","pk":53480},{"il":"RİZE","ilce":"ARDEŞEN","mahalle":"ARKA MAH (ŞENYURT KÖYÜ)","pk":53480},{"il":"RİZE","ilce":"ARDEŞEN","mahalle":"AŞAĞI MAH (ORTAALAN KÖYÜ)","pk":53480},{"il":"RİZE","ilce":"ARDEŞEN","mahalle":"AŞAĞI MAH (ŞENDERE KÖYÜ)","pk":53480},{"il":"RİZE","ilce":"ARDEŞEN","mahalle":"AŞIKLAR MAH (ARMAĞAN KÖYÜ)","pk":53480},{"il":"RİZE","ilce":"ARDEŞEN","mahalle":"BAĞUKUÇHE MAH (ORTAALAN KÖYÜ)","pk":53480},{"il":"RİZE","ilce":"ARDEŞEN","mahalle":"BAHAR MAH","pk":53400},{"il":"RİZE","ilce":"ARDEŞEN","mahalle":"BAHAR MAH (PINARLI KÖYÜ)","pk":53480},{"il":"RİZE","ilce":"ARDEŞEN","mahalle":"BAHAR MAH (YAVUZ KÖYÜ)","pk":53480},{"il":"RİZE","ilce":"ARDEŞEN","mahalle":"BARIŞ MAH","pk":53400},{"il":"RİZE","ilce":"ARDEŞEN","mahalle":"BAŞ MAH","pk":53400},{"il":"RİZE","ilce":"ARDEŞEN","mahalle":"BAŞ MAH (SESLİKAYA KÖYÜ)","pk":53480},{"il":"RİZE","ilce":"ARDEŞEN","mahalle":"BAŞ MAH (ŞENYAMAÇ KÖYÜ)","pk":53480},{"il":"RİZE","ilce":"ARDEŞEN","mahalle":"BERHA MAH (GÜNDOĞAN KÖYÜ)","pk":53480},{"il":"RİZE","ilce":"ARDEŞEN","mahalle":"BÜYÜK MAH (YUKARIDURAK KÖYÜ)","pk":53480},{"il":"RİZE","ilce":"ARDEŞEN","mahalle":"CAMİ ALTI MAH (ŞEHİTLİK KÖYÜ)","pk":53480},{"il":"RİZE","ilce":"ARDEŞEN","mahalle":"CAMİ MAH","pk":53400},{"il":"RİZE","ilce":"ARDEŞEN","mahalle":"CAMİ MAH (BAYIRCIK KÖYÜ)","pk":53480},{"il":"RİZE","ilce":"ARDEŞEN","mahalle":"CAMİ MAH (DUYGULU KÖYÜ)","pk":53480},{"il":"RİZE","ilce":"ARDEŞEN","mahalle":"CAMİ MAH (KÜÇÜKKÖY KÖYÜ)","pk":53480},{"il":"RİZE","ilce":"ARDEŞEN","mahalle":"CAMİ MAH (PINARLI KÖYÜ)","pk":53480},{"il":"RİZE","ilce":"ARDEŞEN","mahalle":"CAMİ MAH (SESLİKAYA KÖYÜ)","pk":53480},{"il":"RİZE","ilce":"ARDEŞEN","mahalle":"CAMİ MAH (ŞENYAMAÇ KÖYÜ)","pk":53480},{"il":"RİZE","ilce":"ARDEŞEN","mahalle":"CAMİ MAH (YAMAÇDERE KÖYÜ)","pk":53480},{"il":"RİZE","ilce":"ARDEŞEN","mahalle":"CAMİ MAH (YAVUZ KÖYÜ)","pk":53480},{"il":"RİZE","ilce":"ARDEŞEN","mahalle":"CAMİ MAH (YENİKÖY KÖYÜ)","pk":53480},{"il":"RİZE","ilce":"ARDEŞEN","mahalle":"CAMİ ÜSTÜ MAH (ŞEHİTLİK KÖYÜ)","pk":53480},{"il":"RİZE","ilce":"ARDEŞEN","mahalle":"CAMİ VE ÇEVRE MAH (AKKAYA KÖYÜ)","pk":53480},{"il":"RİZE","ilce":"ARDEŞEN","mahalle":"CANCA MAH (YAMAÇDERE KÖYÜ)","pk":53480},{"il":"RİZE","ilce":"ARDEŞEN","mahalle":"CENNET MAH (ORTAALAN KÖYÜ)","pk":53480},{"il":"RİZE","ilce":"ARDEŞEN","mahalle":"CİNİZENİ MAH (ÖZGÜR KÖYÜ)","pk":53480},{"il":"RİZE","ilce":"ARDEŞEN","mahalle":"CUMHURİYET MAH","pk":53400},{"il":"RİZE","ilce":"ARDEŞEN","mahalle":"ÇAMLIK MAH (YURTSEVER KÖYÜ)","pk":53480},{"il":"RİZE","ilce":"ARDEŞEN","mahalle":"ÇELİKLER MAH (GÜNDOĞAN KÖYÜ)","pk":53480},{"il":"RİZE","ilce":"ARDEŞEN","mahalle":"ÇIRAKLAR MAH (ÇIRAKLAR KÖYÜ)","pk":53480},{"il":"RİZE","ilce":"ARDEŞEN","mahalle":"ÇIRAKLAR MAH (DOĞANAY KÖYÜ)","pk":53480},{"il":"RİZE","ilce":"ARDEŞEN","mahalle":"ÇİFTEKAVAK MAH","pk":53400},{"il":"RİZE","ilce":"ARDEŞEN","mahalle":"ÇİRİHİNCİ MAH (AŞAĞIDURAK KÖYÜ)","pk":53480},{"il":"RİZE","ilce":"ARDEŞEN","mahalle":"ÇUKURLAR MAH (GÜNEY KÖYÜ)","pk":53480},{"il":"RİZE","ilce":"ARDEŞEN","mahalle":"DEMİRATA MAH (YENİKÖY KÖYÜ)","pk":53480},{"il":"RİZE","ilce":"ARDEŞEN","mahalle":"DENİZ MAH","pk":53400},{"il":"RİZE","ilce":"ARDEŞEN","mahalle":"DENİZ MAH (YENİYOL KÖYÜ)","pk":53480},{"il":"RİZE","ilce":"ARDEŞEN","mahalle":"DENİZLİ MAH (ÇIRAKLAR KÖYÜ)","pk":53480},{"il":"RİZE","ilce":"ARDEŞEN","mahalle":"DERE MAH (BAYIRCIK KÖYÜ)","pk":53480},{"il":"RİZE","ilce":"ARDEŞEN","mahalle":"DERE MAH (ŞEHİTLİK KÖYÜ)","pk":53480},{"il":"RİZE","ilce":"ARDEŞEN","mahalle":"DERE MAH (ŞENYAMAÇ KÖYÜ)","pk":53480},{"il":"RİZE","ilce":"ARDEŞEN","mahalle":"DERE MAH (YAVUZ KÖYÜ)","pk":53480},{"il":"RİZE","ilce":"ARDEŞEN","mahalle":"DERE YEŞİL MAH (SİNAN KÖYÜ)","pk":53480},{"il":"RİZE","ilce":"ARDEŞEN","mahalle":"DEREİÇİ MAH (KAÇKAR KÖYÜ)","pk":53480},{"il":"RİZE","ilce":"ARDEŞEN","mahalle":"DEREMEZRA KÖYÜ","pk":53480},{"il":"RİZE","ilce":"ARDEŞEN","mahalle":"DOBİRA MAH (BAYIRCIK KÖYÜ)","pk":53480},{"il":"RİZE","ilce":"ARDEŞEN","mahalle":"DUATEPE-ALTINTEPE MAH (ARMAĞAN KÖYÜ)","pk":53480},{"il":"RİZE","ilce":"ARDEŞEN","mahalle":"DÜZ MAH","pk":53400},{"il":"RİZE","ilce":"ARDEŞEN","mahalle":"DÜZ MAH (AKKAYA KÖYÜ)","pk":53480},{"il":"RİZE","ilce":"ARDEŞEN","mahalle":"DÜZ MAH (AŞAĞIDURAK KÖYÜ)","pk":53480},{"il":"RİZE","ilce":"ARDEŞEN","mahalle":"DÜZ MAH (BEYAZKAYA KÖYÜ)","pk":53480},{"il":"RİZE","ilce":"ARDEŞEN","mahalle":"DÜZ MAH (GÜNEY KÖYÜ)","pk":53480},{"il":"RİZE","ilce":"ARDEŞEN","mahalle":"DÜZ MAH (MANGANEZ KÖYÜ)","pk":53480},{"il":"RİZE","ilce":"ARDEŞEN","mahalle":"DÜZ MAH (PİRİNÇLİK KÖYÜ)","pk":53480},{"il":"RİZE","ilce":"ARDEŞEN","mahalle":"DÜZ MAH (SESLİKAYA KÖYÜ)","pk":53480},{"il":"RİZE","ilce":"ARDEŞEN","mahalle":"DÜZ MAH (TUNCA BELDESİ)","pk":53490},{"il":"RİZE","ilce":"ARDEŞEN","mahalle":"DÜZ MAH (YAMAÇDERE KÖYÜ)","pk":53480},{"il":"RİZE","ilce":"ARDEŞEN","mahalle":"ELMALIK MAH","pk":53400},{"il":"RİZE","ilce":"ARDEŞEN","mahalle":"ESENTEPE MAH (ORTAALAN KÖYÜ)","pk":53480},{"il":"RİZE","ilce":"ARDEŞEN","mahalle":"ESENTEPE MAH (TUNCA BELDESİ)","pk":53490},{"il":"RİZE","ilce":"ARDEŞEN","mahalle":"ESKİARMUTLUK KÖYÜ","pk":53480},{"il":"RİZE","ilce":"ARDEŞEN","mahalle":"FATİH MAH","pk":53400},{"il":"RİZE","ilce":"ARDEŞEN","mahalle":"FIRTINA MAH","pk":53400},{"il":"RİZE","ilce":"ARDEŞEN","mahalle":"GENÇLER MAH (GÜNDOĞAN KÖYÜ)","pk":53480},{"il":"RİZE","ilce":"ARDEŞEN","mahalle":"GULİVAT MAH (KÖPRÜKÖY KÖYÜ)","pk":53480},{"il":"RİZE","ilce":"ARDEŞEN","mahalle":"GÜNELİ MAH (KÜÇÜKKÖY KÖYÜ)","pk":53480},{"il":"RİZE","ilce":"ARDEŞEN","mahalle":"GÜNEY MAH (YURTSEVER KÖYÜ)","pk":53480},{"il":"RİZE","ilce":"ARDEŞEN","mahalle":"HAŞİMOĞLU MAH (PİRİNÇLİK KÖYÜ)","pk":53480},{"il":"RİZE","ilce":"ARDEŞEN","mahalle":"HOŞDERE KÖYÜ","pk":53480},{"il":"RİZE","ilce":"ARDEŞEN","mahalle":"ILICA MAH (ESKİARMUTLUK KÖYÜ)","pk":53480},{"il":"RİZE","ilce":"ARDEŞEN","mahalle":"IŞIKLI MAH","pk":53480},{"il":"RİZE","ilce":"ARDEŞEN","mahalle":"İNCİRDİP MAH (KÜÇÜKKÖY KÖYÜ)","pk":53480},{"il":"RİZE","ilce":"ARDEŞEN","mahalle":"İSİNA MAH (ÖZGÜR KÖYÜ)","pk":53480},{"il":"RİZE","ilce":"ARDEŞEN","mahalle":"İSLAMOĞLU MAH (DOĞANAY KÖYÜ)","pk":53480},{"il":"RİZE","ilce":"ARDEŞEN","mahalle":"İSMAİLOĞLU MAH (DOĞANAY KÖYÜ)","pk":53480},{"il":"RİZE","ilce":"ARDEŞEN","mahalle":"KAÇKAR KÖYÜ","pk":53480},{"il":"RİZE","ilce":"ARDEŞEN","mahalle":"KAHVECİLER MAH","pk":53400},{"il":"RİZE","ilce":"ARDEŞEN","mahalle":"KALAYİZENİ MAH (KÖPRÜKÖY KÖYÜ)","pk":53480},{"il":"RİZE","ilce":"ARDEŞEN","mahalle":"KANOĞLU MAH (GÜNDOĞAN KÖYÜ)","pk":53480},{"il":"RİZE","ilce":"ARDEŞEN","mahalle":"KARŞI MAH (YEŞİLTEPE KÖYÜ)","pk":53480},{"il":"RİZE","ilce":"ARDEŞEN","mahalle":"KARŞIYAKA MAH (GÜNEY KÖYÜ)","pk":53480},{"il":"RİZE","ilce":"ARDEŞEN","mahalle":"KAVAKLIDERE MAH","pk":53400},{"il":"RİZE","ilce":"ARDEŞEN","mahalle":"KAYABAŞI MAH (ÖNDER KÖYÜ)","pk":53480},{"il":"RİZE","ilce":"ARDEŞEN","mahalle":"KIRAZLIK MAH (ESKİARMUTLUK KÖYÜ)","pk":53480},{"il":"RİZE","ilce":"ARDEŞEN","mahalle":"KİBAROĞLU MAH (DOĞANAY KÖYÜ)","pk":53480},{"il":"RİZE","ilce":"ARDEŞEN","mahalle":"KİRAZLIK KÖYÜ","pk":53480},{"il":"RİZE","ilce":"ARDEŞEN","mahalle":"KOÇOĞLU MAH (ARMAĞAN KÖYÜ)","pk":53480},{"il":"RİZE","ilce":"ARDEŞEN","mahalle":"KODA MAH (PİRİNÇLİK KÖYÜ)","pk":53480},{"il":"RİZE","ilce":"ARDEŞEN","mahalle":"KONAK MAH (TUNCA BELDESİ)","pk":53490},{"il":"RİZE","ilce":"ARDEŞEN","mahalle":"KONAKTEPE MAH","pk":53480},{"il":"RİZE","ilce":"ARDEŞEN","mahalle":"KORZATİ MAH (ORTAALAN KÖYÜ)","pk":53480},{"il":"RİZE","ilce":"ARDEŞEN","mahalle":"KÖPRÜBAŞI MAH (KÖPRÜKÖY KÖYÜ)","pk":53480},{"il":"RİZE","ilce":"ARDEŞEN","mahalle":"KULABERLER MAH (PİRİNÇLİK KÖYÜ)","pk":53480},{"il":"RİZE","ilce":"ARDEŞEN","mahalle":"KULECİLER MAH (GÜNDOĞAN KÖYÜ)","pk":53480},{"il":"RİZE","ilce":"ARDEŞEN","mahalle":"KURTGÖZLÜ MAH (YAMAÇDERE KÖYÜ)","pk":53480},{"il":"RİZE","ilce":"ARDEŞEN","mahalle":"KURTULUŞ KÖYÜ","pk":53480},{"il":"RİZE","ilce":"ARDEŞEN","mahalle":"KUZEY MAH","pk":53400},{"il":"RİZE","ilce":"ARDEŞEN","mahalle":"MERKEZ MAH","pk":53400},{"il":"RİZE","ilce":"ARDEŞEN","mahalle":"MERKEZ MAH (AKDERE KÖYÜ)","pk":53480},{"il":"RİZE","ilce":"ARDEŞEN","mahalle":"MERKEZ MAH (ARMAĞAN KÖYÜ)","pk":53480},{"il":"RİZE","ilce":"ARDEŞEN","mahalle":"MERKEZ MAH (AŞAĞIDURAK KÖYÜ)","pk":53480},{"il":"RİZE","ilce":"ARDEŞEN","mahalle":"MERKEZ MAH (DOĞANAY KÖYÜ)","pk":53480},{"il":"RİZE","ilce":"ARDEŞEN","mahalle":"MERKEZ MAH (KÖPRÜKÖY KÖYÜ)","pk":53480},{"il":"RİZE","ilce":"ARDEŞEN","mahalle":"MERKEZ MAH (KÜÇÜKKÖY KÖYÜ)","pk":53480},{"il":"RİZE","ilce":"ARDEŞEN","mahalle":"MERKEZ MAH (ORTAALAN KÖYÜ)","pk":53480},{"il":"RİZE","ilce":"ARDEŞEN","mahalle":"MERKEZ MAH (ÖZGÜR KÖYÜ)","pk":53480},{"il":"RİZE","ilce":"ARDEŞEN","mahalle":"MERKEZ MAH (PINARLI KÖYÜ)","pk":53480},{"il":"RİZE","ilce":"ARDEŞEN","mahalle":"MERKEZ MAH (SESLİKAYA KÖYÜ)","pk":53480},{"il":"RİZE","ilce":"ARDEŞEN","mahalle":"MERKEZ MAH (SİNAN KÖYÜ)","pk":53480},{"il":"RİZE","ilce":"ARDEŞEN","mahalle":"MERKEZ MAH (ŞENYURT KÖYÜ)","pk":53480},{"il":"RİZE","ilce":"ARDEŞEN","mahalle":"MERKEZ MAH (TUNCA BELDESİ)","pk":53490},{"il":"RİZE","ilce":"ARDEŞEN","mahalle":"MERKEZ MAH (YENİKÖY KÖYÜ)","pk":53480},{"il":"RİZE","ilce":"ARDEŞEN","mahalle":"MERKEZ MAH (YEŞİLTEPE KÖYÜ)","pk":53480},{"il":"RİZE","ilce":"ARDEŞEN","mahalle":"MERKEZ MAH (YURTSEVER KÖYÜ)","pk":53480},{"il":"RİZE","ilce":"ARDEŞEN","mahalle":"MEZRA MAH (YEŞİLTEPE KÖYÜ)","pk":53480},{"il":"RİZE","ilce":"ARDEŞEN","mahalle":"MÜFTÜ MAH","pk":53400},{"il":"RİZE","ilce":"ARDEŞEN","mahalle":"NAVDARLAR MAH (DOĞANAY KÖYÜ)","pk":53480},{"il":"RİZE","ilce":"ARDEŞEN","mahalle":"NIZAMOĞLU MAH (ÖZGÜR KÖYÜ)","pk":53480},{"il":"RİZE","ilce":"ARDEŞEN","mahalle":"OĞUZLAR MAH (GÜNDOĞAN KÖYÜ)","pk":53480},{"il":"RİZE","ilce":"ARDEŞEN","mahalle":"OKUMUŞLAR MAH (YURTSEVER KÖYÜ)","pk":53480},{"il":"RİZE","ilce":"ARDEŞEN","mahalle":"ORTA MAH (AKKAYA KÖYÜ)","pk":53480},{"il":"RİZE","ilce":"ARDEŞEN","mahalle":"ORTA MAH (DOĞANAY KÖYÜ)","pk":53480},{"il":"RİZE","ilce":"ARDEŞEN","mahalle":"ORTA MAH (SESLİKAYA KÖYÜ)","pk":53480},{"il":"RİZE","ilce":"ARDEŞEN","mahalle":"ORTA MAH (ŞENDERE KÖYÜ)","pk":53480},{"il":"RİZE","ilce":"ARDEŞEN","mahalle":"ORTA MAH (TUNCA BELDESİ)","pk":53490},{"il":"RİZE","ilce":"ARDEŞEN","mahalle":"ORTA MAH (YAMAÇDERE KÖYÜ)","pk":53480},{"il":"RİZE","ilce":"ARDEŞEN","mahalle":"ORTA MAH (YAVUZ KÖYÜ)","pk":53480},{"il":"RİZE","ilce":"ARDEŞEN","mahalle":"ORTA MAH (YEŞİLTEPE KÖYÜ)","pk":53480},{"il":"RİZE","ilce":"ARDEŞEN","mahalle":"ORTAmahalle MAH (ARMAĞAN KÖYÜ)","pk":53480},{"il":"RİZE","ilce":"ARDEŞEN","mahalle":"SAHİL MAH (ŞENYURT KÖYÜ)","pk":53480},{"il":"RİZE","ilce":"ARDEŞEN","mahalle":"SERİNDERE KÖYÜ","pk":53480},{"il":"RİZE","ilce":"ARDEŞEN","mahalle":"SHEMRONA MAH (ORTAALAN KÖYÜ)","pk":53480},{"il":"RİZE","ilce":"ARDEŞEN","mahalle":"SIRT MAH (AKKAYA KÖYÜ)","pk":53480},{"il":"RİZE","ilce":"ARDEŞEN","mahalle":"SIRT MAH (AŞAĞIDURAK KÖYÜ)","pk":53480},{"il":"RİZE","ilce":"ARDEŞEN","mahalle":"SIRT MAH (GÜNEY KÖYÜ)","pk":53480},{"il":"RİZE","ilce":"ARDEŞEN","mahalle":"SIRT MAH (ÖZGÜR KÖYÜ)","pk":53480},{"il":"RİZE","ilce":"ARDEŞEN","mahalle":"SIRT MAH (PİRİNÇLİK KÖYÜ)","pk":53480},{"il":"RİZE","ilce":"ARDEŞEN","mahalle":"SULUZENİ MAH (ORTAALAN KÖYÜ)","pk":53480},{"il":"RİZE","ilce":"ARDEŞEN","mahalle":"ŞEFKİBEY MAH (YENİYOL KÖYÜ)","pk":53480},{"il":"RİZE","ilce":"ARDEŞEN","mahalle":"ŞENTEPE MAH","pk":53400},{"il":"RİZE","ilce":"ARDEŞEN","mahalle":"ŞENYUVA MAH (TUNCA BELDESİ)","pk":53490},{"il":"RİZE","ilce":"ARDEŞEN","mahalle":"TAŞ KAPI MAH (ARMAĞAN KÖYÜ)","pk":53480},{"il":"RİZE","ilce":"ARDEŞEN","mahalle":"TAŞBAŞI MAH","pk":53400},{"il":"RİZE","ilce":"ARDEŞEN","mahalle":"TERCÜMANLAR MAH (DUYGULU KÖYÜ)","pk":53480},{"il":"RİZE","ilce":"ARDEŞEN","mahalle":"TOPALOĞLU MAH (DUYGULU KÖYÜ)","pk":53480},{"il":"RİZE","ilce":"ARDEŞEN","mahalle":"TRAMBONA MAH (BAYIRCIK KÖYÜ)","pk":53480},{"il":"RİZE","ilce":"ARDEŞEN","mahalle":"TUTAN MAH (YENİKÖY KÖYÜ)","pk":53480},{"il":"RİZE","ilce":"ARDEŞEN","mahalle":"TÜRBE MAH (SESLİKAYA KÖYÜ)","pk":53480},{"il":"RİZE","ilce":"ARDEŞEN","mahalle":"ÜST MAH (MANGANEZ KÖYÜ)","pk":53480},{"il":"RİZE","ilce":"ARDEŞEN","mahalle":"ÜST MAH (PINARLI KÖYÜ)","pk":53480},{"il":"RİZE","ilce":"ARDEŞEN","mahalle":"ÜST MAH (YENİKÖY KÖYÜ)","pk":53480},{"il":"RİZE","ilce":"ARDEŞEN","mahalle":"YAVUZ SELİM MAH","pk":53400},{"il":"RİZE","ilce":"ARDEŞEN","mahalle":"YAYLA MAH","pk":53400},{"il":"RİZE","ilce":"ARDEŞEN","mahalle":"YENİ MAH","pk":53400},{"il":"RİZE","ilce":"ARDEŞEN","mahalle":"YENİ MAH (KÜÇÜKKÖY KÖYÜ)","pk":53480},{"il":"RİZE","ilce":"ARDEŞEN","mahalle":"YENİ MAH (ŞENYAMAÇ KÖYÜ)","pk":53480},{"il":"RİZE","ilce":"ARDEŞEN","mahalle":"YEŞİLYURT MAH (ARMAĞAN KÖYÜ)","pk":53480},{"il":"RİZE","ilce":"ARDEŞEN","mahalle":"YILDIZLAR MAH (GÜNDOĞAN KÖYÜ)","pk":53480},{"il":"RİZE","ilce":"ARDEŞEN","mahalle":"YUKARI CAMİ MAH (BEYAZKAYA KÖYÜ)","pk":53480},{"il":"RİZE","ilce":"ARDEŞEN","mahalle":"YUKARI MAH (AKKAYA KÖYÜ)","pk":53480},{"il":"RİZE","ilce":"ARDEŞEN","mahalle":"YUKARI MAH (ORTAALAN KÖYÜ)","pk":53480},{"il":"RİZE","ilce":"ARDEŞEN","mahalle":"YUKARI MAH (ŞENDERE KÖYÜ)","pk":53480},{"il":"RİZE","ilce":"ARDEŞEN","mahalle":"YUKARKİ MAH (YENİYOL KÖYÜ)","pk":53480},{"il":"RİZE","ilce":"ARDEŞEN","mahalle":"YÜKSEK MAH (AKDERE KÖYÜ)","pk":53480},{"il":"RİZE","ilce":"ARDEŞEN","mahalle":"ZEYTİNLİK KÖYÜ","pk":53480},{"il":"RİZE","ilce":"ARDEŞEN","mahalle":"ZUMADİ MAH (GÜNDOĞAN KÖYÜ)","pk":53480}]