[{"il":"VAN","ilce":"GEVAŞ","mahalle":"ABALI MAH","pk":65700},{"il":"VAN","ilce":"GEVAŞ","mahalle":"ALADÜZ MAH","pk":65700},{"il":"VAN","ilce":"GEVAŞ","mahalle":"ALTINSAÇ MAH","pk":65700},{"il":"VAN","ilce":"GEVAŞ","mahalle":"ANAKÖY MAH","pk":65700},{"il":"VAN","ilce":"GEVAŞ","mahalle":"ATALAN MAH","pk":65700},{"il":"VAN","ilce":"GEVAŞ","mahalle":"AYDINOCAK MAH","pk":65700},{"il":"VAN","ilce":"GEVAŞ","mahalle":"BAĞLAMA MAH","pk":65700},{"il":"VAN","ilce":"GEVAŞ","mahalle":"BAHÇELİEVLER MAH","pk":65700},{"il":"VAN","ilce":"GEVAŞ","mahalle":"BARIŞIK MAH","pk":65700},{"il":"VAN","ilce":"GEVAŞ","mahalle":"DAĞYÖRE MAH","pk":65700},{"il":"VAN","ilce":"GEVAŞ","mahalle":"DALDERE MAH","pk":65700},{"il":"VAN","ilce":"GEVAŞ","mahalle":"DEĞİRMİTAŞ MAH","pk":65700},{"il":"VAN","ilce":"GEVAŞ","mahalle":"DEREAĞZI MAH","pk":65700},{"il":"VAN","ilce":"GEVAŞ","mahalle":"DİLMETAŞ MAH","pk":65700},{"il":"VAN","ilce":"GEVAŞ","mahalle":"DOKUZAĞAÇ MAH","pk":65700},{"il":"VAN","ilce":"GEVAŞ","mahalle":"ELMALI MAH","pk":65700},{"il":"VAN","ilce":"GEVAŞ","mahalle":"GÖRÜNDÜ MAH","pk":65700},{"il":"VAN","ilce":"GEVAŞ","mahalle":"GÜNDOĞAN MAH","pk":65700},{"il":"VAN","ilce":"GEVAŞ","mahalle":"GÜZELKONAK MAH","pk":65700},{"il":"VAN","ilce":"GEVAŞ","mahalle":"HASBEY MAH","pk":65700},{"il":"VAN","ilce":"GEVAŞ","mahalle":"HİŞET MAH","pk":65700},{"il":"VAN","ilce":"GEVAŞ","mahalle":"İKİZLER MAH","pk":65700},{"il":"VAN","ilce":"GEVAŞ","mahalle":"İNKÖY MAH","pk":65700},{"il":"VAN","ilce":"GEVAŞ","mahalle":"KARŞIYAKA MAH","pk":65700},{"il":"VAN","ilce":"GEVAŞ","mahalle":"KAYALAR MAH","pk":65700},{"il":"VAN","ilce":"GEVAŞ","mahalle":"KAZANÇ MAH","pk":65700},{"il":"VAN","ilce":"GEVAŞ","mahalle":"KIZILTAŞ MAH","pk":65700},{"il":"VAN","ilce":"GEVAŞ","mahalle":"KOÇAK MAH","pk":65700},{"il":"VAN","ilce":"GEVAŞ","mahalle":"KURULTU MAH","pk":65700},{"il":"VAN","ilce":"GEVAŞ","mahalle":"KUŞLUK MAH","pk":65700},{"il":"VAN","ilce":"GEVAŞ","mahalle":"ORTA MAH","pk":65700},{"il":"VAN","ilce":"GEVAŞ","mahalle":"PINARBAŞI MAH","pk":65700},{"il":"VAN","ilce":"GEVAŞ","mahalle":"SELİMİYE MAH","pk":65700},{"il":"VAN","ilce":"GEVAŞ","mahalle":"TİMAR MAH","pk":65700},{"il":"VAN","ilce":"GEVAŞ","mahalle":"TÖRELİ MAH","pk":65700},{"il":"VAN","ilce":"GEVAŞ","mahalle":"UĞURVEREN MAH","pk":65700},{"il":"VAN","ilce":"GEVAŞ","mahalle":"UYSAL MAH","pk":65700},{"il":"VAN","ilce":"GEVAŞ","mahalle":"YANIKÇAY MAH","pk":65700},{"il":"VAN","ilce":"GEVAŞ","mahalle":"YEMİŞLİK MAH","pk":65700},{"il":"VAN","ilce":"GEVAŞ","mahalle":"YOLDÖNDÜ MAH","pk":65700},{"il":"VAN","ilce":"GEVAŞ","mahalle":"YUVA MAH","pk":65700}]