[{"il":"YOZGAT","ilce":"MERKEZ","mahalle":"AGAHEFENDİ MAH","pk":66100},{"il":"YOZGAT","ilce":"MERKEZ","mahalle":"AKTAŞ KÖYÜ","pk":66010},{"il":"YOZGAT","ilce":"MERKEZ","mahalle":"AKYAMAÇ KÖYÜ","pk":66010},{"il":"YOZGAT","ilce":"MERKEZ","mahalle":"ALEMDAR KÖYÜ","pk":66010},{"il":"YOZGAT","ilce":"MERKEZ","mahalle":"ARAPLIÇİFTLİĞİ MAH (DAYILI KÖYÜ)","pk":66010},{"il":"YOZGAT","ilce":"MERKEZ","mahalle":"AŞAĞI ÇATAK MAH","pk":66100},{"il":"YOZGAT","ilce":"MERKEZ","mahalle":"AŞAĞINOHUTLU MAH","pk":66100},{"il":"YOZGAT","ilce":"MERKEZ","mahalle":"AYDOĞAN KÖYÜ","pk":66010},{"il":"YOZGAT","ilce":"MERKEZ","mahalle":"AZİZLİ KÖYÜ","pk":66010},{"il":"YOZGAT","ilce":"MERKEZ","mahalle":"AZİZLİBAĞLARI MAH","pk":66010},{"il":"YOZGAT","ilce":"MERKEZ","mahalle":"BACILI KÖYÜ","pk":66010},{"il":"YOZGAT","ilce":"MERKEZ","mahalle":"BAHÇECİK KÖYÜ","pk":66010},{"il":"YOZGAT","ilce":"MERKEZ","mahalle":"BAHÇELİEVLER MAH (ESENLİ KÖYÜ)","pk":66010},{"il":"YOZGAT","ilce":"MERKEZ","mahalle":"BAHÇEŞEHİR MAH","pk":66100},{"il":"YOZGAT","ilce":"MERKEZ","mahalle":"BAŞIBÜYÜKLÜ KÖYÜ","pk":66010},{"il":"YOZGAT","ilce":"MERKEZ","mahalle":"BAŞINAYAYLA KÖYÜ","pk":66010},{"il":"YOZGAT","ilce":"MERKEZ","mahalle":"BATTAL KÖYÜ","pk":66010},{"il":"YOZGAT","ilce":"MERKEZ","mahalle":"BAYATÖREN KÖYÜ","pk":66010},{"il":"YOZGAT","ilce":"MERKEZ","mahalle":"BEYVELİOĞLU KÖYÜ","pk":66010},{"il":"YOZGAT","ilce":"MERKEZ","mahalle":"BİLAL ŞAHİN MAH","pk":66100},{"il":"YOZGAT","ilce":"MERKEZ","mahalle":"BOZLAR KÖYÜ","pk":66010},{"il":"YOZGAT","ilce":"MERKEZ","mahalle":"BUZAĞCIOĞLU KÖYÜ","pk":66010},{"il":"YOZGAT","ilce":"MERKEZ","mahalle":"BÜYÜKİNCİRLİ KÖYÜ","pk":66010},{"il":"YOZGAT","ilce":"MERKEZ","mahalle":"BÜYÜKMAHAL KÖYÜ","pk":66010},{"il":"YOZGAT","ilce":"MERKEZ","mahalle":"BÜYÜKNEFES KÖYÜ","pk":66010},{"il":"YOZGAT","ilce":"MERKEZ","mahalle":"CAMİ MAH (OSMANPAŞA KÖYÜ)","pk":66010},{"il":"YOZGAT","ilce":"MERKEZ","mahalle":"CİHANPAŞA KÖYÜ","pk":66010},{"il":"YOZGAT","ilce":"MERKEZ","mahalle":"ÇAĞLAYAN KÖYÜ","pk":66010},{"il":"YOZGAT","ilce":"MERKEZ","mahalle":"ÇALATLI KÖYÜ","pk":66010},{"il":"YOZGAT","ilce":"MERKEZ","mahalle":"ÇALILI KÖYÜ","pk":66010},{"il":"YOZGAT","ilce":"MERKEZ","mahalle":"ÇAPANOĞLU MAH","pk":66100},{"il":"YOZGAT","ilce":"MERKEZ","mahalle":"ÇAY MAH (ESENLİ KÖYÜ)","pk":66010},{"il":"YOZGAT","ilce":"MERKEZ","mahalle":"ÇIRADERESİ MAH (DERBENT KÖYÜ)","pk":66010},{"il":"YOZGAT","ilce":"MERKEZ","mahalle":"ÇORAK KÖYÜ","pk":66010},{"il":"YOZGAT","ilce":"MERKEZ","mahalle":"DAĞYENİCESİ KÖYÜ","pk":66010},{"il":"YOZGAT","ilce":"MERKEZ","mahalle":"DAMBASAN KÖYÜ","pk":66010},{"il":"YOZGAT","ilce":"MERKEZ","mahalle":"DARICI KÖYÜ","pk":66010},{"il":"YOZGAT","ilce":"MERKEZ","mahalle":"DELİHASANLI KÖYÜ","pk":66010},{"il":"YOZGAT","ilce":"MERKEZ","mahalle":"DEREBOYMUL KÖYÜ","pk":66010},{"il":"YOZGAT","ilce":"MERKEZ","mahalle":"DEREKIŞLA KÖYÜ","pk":66010},{"il":"YOZGAT","ilce":"MERKEZ","mahalle":"DEREMAHAL KÖYÜ","pk":66010},{"il":"YOZGAT","ilce":"MERKEZ","mahalle":"DEREMUMLU KÖYÜ","pk":66010},{"il":"YOZGAT","ilce":"MERKEZ","mahalle":"DEVELİK MAH","pk":66100},{"il":"YOZGAT","ilce":"MERKEZ","mahalle":"DİVANLI MAH","pk":66010},{"il":"YOZGAT","ilce":"MERKEZ","mahalle":"DÖNEDERESİ MAH (TÜRKMENSARILAR KÖYÜ)","pk":66010},{"il":"YOZGAT","ilce":"MERKEZ","mahalle":"ERDOĞAN AKDAĞ MAH","pk":66100},{"il":"YOZGAT","ilce":"MERKEZ","mahalle":"ERKEKLİ KÖYÜ","pk":66010},{"il":"YOZGAT","ilce":"MERKEZ","mahalle":"ESKİPAZAR MAH","pk":66100},{"il":"YOZGAT","ilce":"MERKEZ","mahalle":"EVCİ KÖYÜ","pk":66010},{"il":"YOZGAT","ilce":"MERKEZ","mahalle":"FAKIBEYLİ KÖYÜ","pk":66010},{"il":"YOZGAT","ilce":"MERKEZ","mahalle":"FATİH MAH","pk":66100},{"il":"YOZGAT","ilce":"MERKEZ","mahalle":"GELİNGÜLLÜ MAH (ESENLİ KÖYÜ)","pk":66010},{"il":"YOZGAT","ilce":"MERKEZ","mahalle":"GEVREK KÖYÜ","pk":66010},{"il":"YOZGAT","ilce":"MERKEZ","mahalle":"GÖKÇEKIŞLA KÖYÜ","pk":66010},{"il":"YOZGAT","ilce":"MERKEZ","mahalle":"GÖRPELİ KÖYÜ","pk":66010},{"il":"YOZGAT","ilce":"MERKEZ","mahalle":"GÜDÜLELMAHACILI KÖYÜ","pk":66010},{"il":"YOZGAT","ilce":"MERKEZ","mahalle":"GÜLLÜK KÖYÜ","pk":66010},{"il":"YOZGAT","ilce":"MERKEZ","mahalle":"GÜLLÜOLUK KÖYÜ","pk":66010},{"il":"YOZGAT","ilce":"MERKEZ","mahalle":"GÜNEŞLİ KÖYÜ","pk":66010},{"il":"YOZGAT","ilce":"MERKEZ","mahalle":"HAMZALI KÖYÜ","pk":66010},{"il":"YOZGAT","ilce":"MERKEZ","mahalle":"HAYDARBEYLİ KÖYÜ","pk":66010},{"il":"YOZGAT","ilce":"MERKEZ","mahalle":"İNCEÇAYIR KÖYÜ","pk":66010},{"il":"YOZGAT","ilce":"MERKEZ","mahalle":"İSTANBULLUOĞLU MAH","pk":66100},{"il":"YOZGAT","ilce":"MERKEZ","mahalle":"İŞLEĞEN KÖYÜ","pk":66010},{"il":"YOZGAT","ilce":"MERKEZ","mahalle":"KABABEL KÖYÜ","pk":66010},{"il":"YOZGAT","ilce":"MERKEZ","mahalle":"KALE KÖYÜ","pk":66010},{"il":"YOZGAT","ilce":"MERKEZ","mahalle":"KALINBÜK MAH (BİŞEK KÖYÜ)","pk":66010},{"il":"YOZGAT","ilce":"MERKEZ","mahalle":"KARABIYIK KÖYÜ","pk":66010},{"il":"YOZGAT","ilce":"MERKEZ","mahalle":"KARACALAR KÖYÜ","pk":66010},{"il":"YOZGAT","ilce":"MERKEZ","mahalle":"KARALAR KÖYÜ","pk":66010},{"il":"YOZGAT","ilce":"MERKEZ","mahalle":"KARALAR MAH (ÇADIRARDIÇ KÖYÜ)","pk":66010},{"il":"YOZGAT","ilce":"MERKEZ","mahalle":"KARATEPE MAH","pk":66100},{"il":"YOZGAT","ilce":"MERKEZ","mahalle":"KARŞIYAKA MAH (ESENLİ KÖYÜ)","pk":66010},{"il":"YOZGAT","ilce":"MERKEZ","mahalle":"KAŞKIŞLA KÖYÜ","pk":66010},{"il":"YOZGAT","ilce":"MERKEZ","mahalle":"KAVURGALI KÖYÜ","pk":66010},{"il":"YOZGAT","ilce":"MERKEZ","mahalle":"KIRIKSOKU KÖYÜ","pk":66010},{"il":"YOZGAT","ilce":"MERKEZ","mahalle":"KIŞLA KÖYÜ","pk":66010},{"il":"YOZGAT","ilce":"MERKEZ","mahalle":"KIZILTEPE KÖYÜ","pk":66010},{"il":"YOZGAT","ilce":"MERKEZ","mahalle":"KİLLİK MAH (GÜLYAYLA KÖYÜ)","pk":66010},{"il":"YOZGAT","ilce":"MERKEZ","mahalle":"KOLANLI KÖYÜ","pk":66010},{"il":"YOZGAT","ilce":"MERKEZ","mahalle":"KOYUNCULU KÖYÜ","pk":66010},{"il":"YOZGAT","ilce":"MERKEZ","mahalle":"KÖÇEKKÖMÜ KÖYÜ","pk":66010},{"il":"YOZGAT","ilce":"MERKEZ","mahalle":"KÖÇEKLİOĞLU KÖYÜ","pk":66010},{"il":"YOZGAT","ilce":"MERKEZ","mahalle":"KÖKLÜ MAH (BALTASARILAR KÖYÜ)","pk":66010},{"il":"YOZGAT","ilce":"MERKEZ","mahalle":"KÖSEOĞLU MAH","pk":66100},{"il":"YOZGAT","ilce":"MERKEZ","mahalle":"KÖSEYUSUFLU KÖYÜ","pk":66010},{"il":"YOZGAT","ilce":"MERKEZ","mahalle":"KUŞCU KÖYÜ","pk":66010},{"il":"YOZGAT","ilce":"MERKEZ","mahalle":"KUYUMCU KÖYÜ","pk":66010},{"il":"YOZGAT","ilce":"MERKEZ","mahalle":"LÖK KÖYÜ","pk":66010},{"il":"YOZGAT","ilce":"MERKEZ","mahalle":"MEDRESE MAH","pk":66100},{"il":"YOZGAT","ilce":"MERKEZ","mahalle":"MEHMET HULUSİ EFENDİ MAH","pk":66100},{"il":"YOZGAT","ilce":"MERKEZ","mahalle":"MERKEZ MAH (BALTASARILAR KÖYÜ)","pk":66010},{"il":"YOZGAT","ilce":"MERKEZ","mahalle":"MERKEZ MAH (BİŞEK KÖYÜ)","pk":66010},{"il":"YOZGAT","ilce":"MERKEZ","mahalle":"MERKEZ MAH (ÇADIRARDIÇ KÖYÜ)","pk":66010},{"il":"YOZGAT","ilce":"MERKEZ","mahalle":"MERKEZ MAH (ÇATMA KÖYÜ)","pk":66010},{"il":"YOZGAT","ilce":"MERKEZ","mahalle":"MERKEZ MAH (DAYILI KÖYÜ)","pk":66010},{"il":"YOZGAT","ilce":"MERKEZ","mahalle":"MERKEZ MAH (DERBENT KÖYÜ)","pk":66010},{"il":"YOZGAT","ilce":"MERKEZ","mahalle":"MERKEZ MAH (GÜLYAYLA KÖYÜ)","pk":66010},{"il":"YOZGAT","ilce":"MERKEZ","mahalle":"MERKEZ MAH (KIRIM KÖYÜ)","pk":66010},{"il":"YOZGAT","ilce":"MERKEZ","mahalle":"MERKEZ MAH (TÜRKMENSARILAR KÖYÜ)","pk":66010},{"il":"YOZGAT","ilce":"MERKEZ","mahalle":"MEZRAA KÖYÜ","pk":66010},{"il":"YOZGAT","ilce":"MERKEZ","mahalle":"MOLLAHASAN MAH (KIRIM KÖYÜ)","pk":66010},{"il":"YOZGAT","ilce":"MERKEZ","mahalle":"MUSABEYLİ KÖYÜ","pk":66010},{"il":"YOZGAT","ilce":"MERKEZ","mahalle":"MUSABEYLİBOĞAZI KÖYÜ","pk":66010},{"il":"YOZGAT","ilce":"MERKEZ","mahalle":"MUTAFOĞLU MAH","pk":66100},{"il":"YOZGAT","ilce":"MERKEZ","mahalle":"ÖRENCİK KÖYÜ","pk":66010},{"il":"YOZGAT","ilce":"MERKEZ","mahalle":"ÖZLÜCE KÖYÜ","pk":66010},{"il":"YOZGAT","ilce":"MERKEZ","mahalle":"PENBECİK KÖYÜ","pk":66010},{"il":"YOZGAT","ilce":"MERKEZ","mahalle":"RECEPLİ KÖYÜ","pk":66010},{"il":"YOZGAT","ilce":"MERKEZ","mahalle":"SAĞLIK KÖYÜ","pk":66010},{"il":"YOZGAT","ilce":"MERKEZ","mahalle":"SALMANFAKILI KÖYÜ","pk":66010},{"il":"YOZGAT","ilce":"MERKEZ","mahalle":"SARIFATMA KÖYÜ","pk":66010},{"il":"YOZGAT","ilce":"MERKEZ","mahalle":"SARIHACILI MAH","pk":66010},{"il":"YOZGAT","ilce":"MERKEZ","mahalle":"SARIMBEY KÖYÜ","pk":66010},{"il":"YOZGAT","ilce":"MERKEZ","mahalle":"SARININÖREN KÖYÜ","pk":66010},{"il":"YOZGAT","ilce":"MERKEZ","mahalle":"SÖĞÜTLÜYAYLA KÖYÜ","pk":66010},{"il":"YOZGAT","ilce":"MERKEZ","mahalle":"ŞEHİTLER MAH (OSMANPAŞA KÖYÜ)","pk":66010},{"il":"YOZGAT","ilce":"MERKEZ","mahalle":"ŞEYH AHMET EFENDİ MAH","pk":66010},{"il":"YOZGAT","ilce":"MERKEZ","mahalle":"ŞEYHOSMAN MAH","pk":66100},{"il":"YOZGAT","ilce":"MERKEZ","mahalle":"TAŞKÖPRÜ MAH","pk":66100},{"il":"YOZGAT","ilce":"MERKEZ","mahalle":"TAYFUR KÖYÜ","pk":66010},{"il":"YOZGAT","ilce":"MERKEZ","mahalle":"TAYIP KÖYÜ","pk":66010},{"il":"YOZGAT","ilce":"MERKEZ","mahalle":"TEKKE MAH","pk":66100},{"il":"YOZGAT","ilce":"MERKEZ","mahalle":"TEKKE MAH (OSMANPAŞA KÖYÜ)","pk":66010},{"il":"YOZGAT","ilce":"MERKEZ","mahalle":"TEKKEYENİCESİ KÖYÜ","pk":66010},{"il":"YOZGAT","ilce":"MERKEZ","mahalle":"TOPAÇ KÖYÜ","pk":66010},{"il":"YOZGAT","ilce":"MERKEZ","mahalle":"TOPCU KÖYÜ","pk":66010},{"il":"YOZGAT","ilce":"MERKEZ","mahalle":"TUZKAYA MAH","pk":66100},{"il":"YOZGAT","ilce":"MERKEZ","mahalle":"TÜRKMEN KÖYÜ","pk":66010},{"il":"YOZGAT","ilce":"MERKEZ","mahalle":"YASSIHÜYÜK KÖYÜ","pk":66010},{"il":"YOZGAT","ilce":"MERKEZ","mahalle":"YAZPINAR KÖYÜ","pk":66010},{"il":"YOZGAT","ilce":"MERKEZ","mahalle":"YENİCAMİ MAH","pk":66100},{"il":"YOZGAT","ilce":"MERKEZ","mahalle":"YEŞİLOVA KÖYÜ","pk":66010},{"il":"YOZGAT","ilce":"MERKEZ","mahalle":"YUDAN KÖYÜ","pk":66010},{"il":"YOZGAT","ilce":"MERKEZ","mahalle":"YUKARI ÇATMA MAH (ÇATMA KÖYÜ)","pk":66010},{"il":"YOZGAT","ilce":"MERKEZ","mahalle":"YUKARIÇATAK MAH","pk":66100},{"il":"YOZGAT","ilce":"MERKEZ","mahalle":"YUKARINOHUTLU MAH","pk":66100}]