[{"il":"ÇANAKKALE","ilce":"ECEABAT","mahalle":"AHILDERE ALTI MAH (YALOVA KÖYÜ)","pk":17902},{"il":"ÇANAKKALE","ilce":"ECEABAT","mahalle":"ALÇITEPE KÖYÜ","pk":17902},{"il":"ÇANAKKALE","ilce":"ECEABAT","mahalle":"AZMAK MAH (SEDDÜLBAHİR KÖYÜ)","pk":17902},{"il":"ÇANAKKALE","ilce":"ECEABAT","mahalle":"BAŞÇEŞME MAH (SEDDÜLBAHİR KÖYÜ)","pk":17902},{"il":"ÇANAKKALE","ilce":"ECEABAT","mahalle":"BEHRAMLI KÖYÜ","pk":17902},{"il":"ÇANAKKALE","ilce":"ECEABAT","mahalle":"BEŞYOL KÖYÜ","pk":17902},{"il":"ÇANAKKALE","ilce":"ECEABAT","mahalle":"BİGALI KÖYÜ","pk":17902},{"il":"ÇANAKKALE","ilce":"ECEABAT","mahalle":"BOYACIBURNU YALILAR MAH (YALOVA KÖYÜ)","pk":17902},{"il":"ÇANAKKALE","ilce":"ECEABAT","mahalle":"BÜYÜKANAFARTA KÖYÜ","pk":17902},{"il":"ÇANAKKALE","ilce":"ECEABAT","mahalle":"GÖZTEPE MAH (SEDDÜLBAHİR KÖYÜ)","pk":17902},{"il":"ÇANAKKALE","ilce":"ECEABAT","mahalle":"İSMETPAŞA MAH","pk":17900},{"il":"ÇANAKKALE","ilce":"ECEABAT","mahalle":"KEMALPAŞA MAH","pk":17900},{"il":"ÇANAKKALE","ilce":"ECEABAT","mahalle":"KOCADERE KÖYÜ","pk":17902},{"il":"ÇANAKKALE","ilce":"ECEABAT","mahalle":"KUMKÖY KÖYÜ","pk":17902},{"il":"ÇANAKKALE","ilce":"ECEABAT","mahalle":"KÜÇÜKANAFARTA KÖYÜ","pk":17902},{"il":"ÇANAKKALE","ilce":"ECEABAT","mahalle":"MERKEZ MAH (KİLİDÜLBAHİR KÖYÜ)","pk":17902},{"il":"ÇANAKKALE","ilce":"ECEABAT","mahalle":"MORTO KOYU MAH (SEDDÜLBAHİR KÖYÜ)","pk":17902},{"il":"ÇANAKKALE","ilce":"ECEABAT","mahalle":"SEDDÜLBAHİR DUASI MAH (SEDDÜLBAHİR KÖYÜ)","pk":17902},{"il":"ÇANAKKALE","ilce":"ECEABAT","mahalle":"SEDDÜLBAHİR KÖYÜ","pk":17902},{"il":"ÇANAKKALE","ilce":"ECEABAT","mahalle":"TEKKE MAH (SEDDÜLBAHİR KÖYÜ)","pk":17902},{"il":"ÇANAKKALE","ilce":"ECEABAT","mahalle":"YALOVA KÖYÜ","pk":17902},{"il":"ÇANAKKALE","ilce":"ECEABAT","mahalle":"YOLAĞZI KÖYÜ","pk":17902},{"il":"ÇANAKKALE","ilce":"ECEABAT","mahalle":"ZIĞINDERE MAH (SEDDÜLBAHİR KÖYÜ)","pk":17902}]